{
    "serializationData": {
        "SerializedFormat": 0,
        "SerializedBytes": [],
        "ReferencedUnityObjects": [],
        "SerializedBytesString": "",
        "Prefab": {
            "instanceID": 0
        },
        "PrefabModificationsReferencedUnityObjects": [],
        "PrefabModifications": [],
        "SerializationNodes": []
    },
    "nodes": [
        {
            "rid": 1000
        },
        {
            "rid": 1001
        },
        {
            "rid": 1002
        },
        {
            "rid": 1003
        },
        {
            "rid": 1004
        },
        {
            "rid": 1005
        },
        {
            "rid": 1006
        },
        {
            "rid": 1007
        },
        {
            "rid": 1008
        },
        {
            "rid": 1009
        },
        {
            "rid": 1010
        },
        {
            "rid": 1011
        },
        {
            "rid": 1012
        },
        {
            "rid": 1013
        },
        {
            "rid": 1014
        },
        {
            "rid": 1015
        },
        {
            "rid": 1016
        },
        {
            "rid": 1017
        },
        {
            "rid": 1018
        },
        {
            "rid": 1019
        }
    ],
    "edges": [
        {
            "GUID": "32c21acf-6a48-4e2d-a599-036b686a30ea",
            "inputNodeGUID": "19a6feac-1806-46b2-ae4a-bd2f8e160626",
            "outputNodeGUID": "94189406-a2af-4783-aa47-dc9fa23be3bb",
            "inputFieldName": "ID",
            "outputFieldName": "PackedParamsOutput",
            "inputPortIdentifier": "0",
            "outputPortIdentifier": "1",
            "isVisible": true
        },
        {
            "GUID": "d8901905-ce33-4708-9e85-0bff41fa4d2c",
            "inputNodeGUID": "3cf70409-dbb7-4690-ac45-7aa843e2ea54",
            "outputNodeGUID": "4d860b7f-5410-4333-850c-dde8b1c5c5b4",
            "inputFieldName": "ID",
            "outputFieldName": "PackedParamsOutput",
            "inputPortIdentifier": "0",
            "outputPortIdentifier": "0",
            "isVisible": true
        },
        {
            "GUID": "129f8c6e-5dd3-461f-bdb5-5c59d5ac8fe0",
            "inputNodeGUID": "32ad969a-9c48-4bbd-a6c2-cb9ea132ef50",
            "outputNodeGUID": "9b5fdd87-8c63-4bee-9ff5-56ab7e54cc81",
            "inputFieldName": "ID",
            "outputFieldName": "PackedParamsOutput",
            "inputPortIdentifier": "0",
            "outputPortIdentifier": "0",
            "isVisible": true
        },
        {
            "GUID": "9fbf191d-f0ed-49e8-a86b-577e2c03f102",
            "inputNodeGUID": "1c25095d-8311-4337-ae2d-0103356239bb",
            "outputNodeGUID": "a8df796d-8050-4675-8e48-dd90c525744e",
            "inputFieldName": "ID",
            "outputFieldName": "PackedParamsOutput",
            "inputPortIdentifier": "0",
            "outputPortIdentifier": "0",
            "isVisible": true
        },
        {
            "GUID": "4e04b32d-2c75-4e8f-8f16-e6aa3ae2511a",
            "inputNodeGUID": "ab0952c2-cbf6-40ce-8128-568db3b69b1b",
            "outputNodeGUID": "720055a5-7f2d-426c-b185-37d05070feda",
            "inputFieldName": "ID",
            "outputFieldName": "PackedParamsOutput",
            "inputPortIdentifier": "0",
            "outputPortIdentifier": "0",
            "isVisible": true
        },
        {
            "GUID": "1742acad-db7f-4882-854f-a3605f4461e4",
            "inputNodeGUID": "342f3264-fb8f-47eb-a07b-13a054e615f1",
            "outputNodeGUID": "e358e457-e288-4209-91cf-3f6216fa17aa",
            "inputFieldName": "ID",
            "outputFieldName": "PackedParamsOutput",
            "inputPortIdentifier": "0",
            "outputPortIdentifier": "0",
            "isVisible": true
        },
        {
            "GUID": "2ce30446-ad66-44bd-83d5-6ae3d6d82116",
            "inputNodeGUID": "05b1c01e-35a7-4385-9b44-0e44a7f5ef98",
            "outputNodeGUID": "342f3264-fb8f-47eb-a07b-13a054e615f1",
            "inputFieldName": "ID",
            "outputFieldName": "PackedParamsOutput",
            "inputPortIdentifier": "0",
            "outputPortIdentifier": "4",
            "isVisible": true
        },
        {
            "GUID": "af304551-a60d-45fe-a6e7-c9ef934145f6",
            "inputNodeGUID": "ee0cc5ee-8b7b-4e43-b68b-f07af5628f0f",
            "outputNodeGUID": "05b1c01e-35a7-4385-9b44-0e44a7f5ef98",
            "inputFieldName": "ID",
            "outputFieldName": "PackedParamsOutput",
            "inputPortIdentifier": "0",
            "outputPortIdentifier": "0",
            "isVisible": true
        },
        {
            "GUID": "d54d10d7-b699-4c53-9b57-81a73b444a0f",
            "inputNodeGUID": "e3646843-cc08-4ba4-8cd8-dee5a1b70c98",
            "outputNodeGUID": "f34d7ed3-01ed-4010-9add-073d28727575",
            "inputFieldName": "ID",
            "outputFieldName": "PackedParamsOutput",
            "inputPortIdentifier": "0",
            "outputPortIdentifier": "2",
            "isVisible": true
        },
        {
            "GUID": "54a0000d-8852-4dbd-97a2-f0e420add97d",
            "inputNodeGUID": "c57a169c-50fc-4779-aac2-e429890b6eed",
            "outputNodeGUID": "342f3264-fb8f-47eb-a07b-13a054e615f1",
            "inputFieldName": "ID",
            "outputFieldName": "PackedParamsOutput",
            "inputPortIdentifier": "0",
            "outputPortIdentifier": "1",
            "isVisible": true
        },
        {
            "GUID": "66ebb346-f22b-4da1-b238-2eda83f3ae45",
            "inputNodeGUID": "f34d7ed3-01ed-4010-9add-073d28727575",
            "outputNodeGUID": "c57a169c-50fc-4779-aac2-e429890b6eed",
            "inputFieldName": "ID",
            "outputFieldName": "PackedParamsOutput",
            "inputPortIdentifier": "0",
            "outputPortIdentifier": "0",
            "isVisible": true
        },
        {
            "GUID": "23c79dcd-0c4f-4e0e-99a4-a6e4d7216daa",
            "inputNodeGUID": "9b5fdd87-8c63-4bee-9ff5-56ab7e54cc81",
            "outputNodeGUID": "19a6feac-1806-46b2-ae4a-bd2f8e160626",
            "inputFieldName": "ID",
            "outputFieldName": "PackedParamsOutput",
            "inputPortIdentifier": "0",
            "outputPortIdentifier": "2",
            "isVisible": true
        },
        {
            "GUID": "93029299-3b1e-4fdc-8984-fc11f7342204",
            "inputNodeGUID": "94189406-a2af-4783-aa47-dc9fa23be3bb",
            "outputNodeGUID": "c57a169c-50fc-4779-aac2-e429890b6eed",
            "inputFieldName": "ID",
            "outputFieldName": "PackedParamsOutput",
            "inputPortIdentifier": "0",
            "outputPortIdentifier": "0",
            "isVisible": true
        },
        {
            "GUID": "07c09d0b-7221-4152-9d55-626068adafe1",
            "inputNodeGUID": "a8df796d-8050-4675-8e48-dd90c525744e",
            "outputNodeGUID": "05b1c01e-35a7-4385-9b44-0e44a7f5ef98",
            "inputFieldName": "ID",
            "outputFieldName": "PackedParamsOutput",
            "inputPortIdentifier": "0",
            "outputPortIdentifier": "0",
            "isVisible": true
        },
        {
            "GUID": "2c543dd1-de51-4539-8fe8-fff49cafbb56",
            "inputNodeGUID": "4d860b7f-5410-4333-850c-dde8b1c5c5b4",
            "outputNodeGUID": "94189406-a2af-4783-aa47-dc9fa23be3bb",
            "inputFieldName": "ID",
            "outputFieldName": "PackedParamsOutput",
            "inputPortIdentifier": "0",
            "outputPortIdentifier": "4",
            "isVisible": true
        },
        {
            "GUID": "a820018f-0659-41be-bd0c-2ade78465f7d",
            "inputNodeGUID": "720055a5-7f2d-426c-b185-37d05070feda",
            "outputNodeGUID": "4d860b7f-5410-4333-850c-dde8b1c5c5b4",
            "inputFieldName": "ID",
            "outputFieldName": "PackedParamsOutput",
            "inputPortIdentifier": "0",
            "outputPortIdentifier": "0",
            "isVisible": true
        },
        {
            "GUID": "38e3e8d5-22d0-4320-94fb-2f8669951ed9",
            "inputNodeGUID": "e358e457-e288-4209-91cf-3f6216fa17aa",
            "outputNodeGUID": "ab1f4f8a-80e3-4d4c-b75b-264c72ad7ba5",
            "inputFieldName": "ID",
            "outputFieldName": "PackedMembersOutput",
            "inputPortIdentifier": "0",
            "outputPortIdentifier": "SkillEffectPassiveExecuteInfo.SkillEffectConfigID",
            "isVisible": true
        },
        {
            "GUID": "e76ae2d3-e2f6-49cc-80f4-894994d30762",
            "inputNodeGUID": "174780ca-2d03-4cf4-839e-8fd358332389",
            "outputNodeGUID": "e358e457-e288-4209-91cf-3f6216fa17aa",
            "inputFieldName": "ID",
            "outputFieldName": "PackedParamsOutput",
            "inputPortIdentifier": "0",
            "outputPortIdentifier": "0",
            "isVisible": true
        }
    ],
    "groups": [
        {
            "GUID": "126dd571-7dad-45e9-a89c-81edc3164f0c",
            "title": "创建一个变量参数，控制增伤比例",
            "color": {
                "r": 0.0,
                "g": 0.0,
                "b": 0.0,
                "a": 0.30000001192092898
            },
            "position": {
                "serializedVersion": "2",
                "x": 861.8978271484375,
                "y": -647.4989624023438,
                "width": 434.999755859375,
                "height": 181.99990844726563
            },
            "size": {
                "x": 400.0,
                "y": 200.0
            },
            "innerNodeGUIDs": [
                "baf032c0-3de6-4af9-9614-861804b07c5e"
            ],
            "innerStickyNoteGUIDs": []
        }
    ],
    "stackNodes": [],
    "pinnedElements": [
        {
            "position": {
                "serializedVersion": "2",
                "x": 0.0,
                "y": 32.0,
                "width": 542.0,
                "height": 244.0
            },
            "opened": true,
            "editorType": {
                "serializedType": "NodeEditor.ConfigPinnedView, NodeEditor, Version=0.0.0.0, Culture=neutral, PublicKeyToken=null"
            }
        }
    ],
    "exposedParameters": [],
    "serializedParameterList": [],
    "stickyNotes": [],
    "curTab": 3,
    "path": "Assets/Thirds/NodeEditor/SkillEditor/Saves/Jsons/法宝/SkillGraph_400002【法器真诀】鸿都秘术.json",
    "references": {
        "version": 2,
        "RefIds": [
            {
                "rid": 1000,
                "type": {
                    "class": "SkillConfigNode",
                    "ns": "NodeEditor",
                    "asm": "NodeEditor"
                },
                "data": {
                    "GUID": "ab1f4f8a-80e3-4d4c-b75b-264c72ad7ba5",
                    "computeOrder": 0,
                    "position": {
                        "serializedVersion": "2",
                        "x": 360.0,
                        "y": 153.0,
                        "width": 334.0,
                        "height": 239.0
                    },
                    "expanded": false,
                    "debug": false,
                    "nodeLock": false,
                    "visible": true,
                    "hideChildNodes": false,
                    "hidePos": {
                        "x": 0.0,
                        "y": 0.0
                    },
                    "hideCounter": 0,
                    "ID": 400002,
                    "Desc": "",
                    "IsTemplate": false,
                    "TemplateFlags": 0,
                    "TemplateParams": [],
                    "TemplateParamsDesc": [],
                    "TemplateParamsCustomAdd": false,
                    "TableTash": "0C2C5D4A7DC9280429315C2EEAD44FDF",
                    "ConfigJson": "{\"SkillXinfaType\":0,\"ID\":400002,\"SkillNameKey\":0,\"SkillDescKey\":0,\"Icon\":\"\",\"ElementType\":0,\"SkillSchoolResType\":0,\"FeatureLabel\":0,\"BDLabels\":[],\"SkillAITags\":[],\"DamageType\":0,\"SkillMainType\":5,\"SkillSubType\":501,\"MPCost\":0,\"HunLiValue\":0,\"SectXinfaEnergyValue\":0,\"SkillCastFrame\":0,\"SkillBufferStartFrame\":0,\"SkillBufferFrame\":0,\"SkillBaseDuration\":0,\"SkillCastIsNotInterruptable\":false,\"IsSkillBufferFrameCanMove\":false,\"CdType\":0,\"CdTime\":0,\"ComboCdList\":[],\"CDMaxStoreCount\":0,\"SkillFixCdTime\":0,\"SkillRange\":0,\"SkillMinRange\":0,\"AISkillRange\":0,\"ExtraAlertRange\":0,\"IsCloseChaseInAlertRange\":false,\"NeedTargetInRange\":false,\"IsSkillCastNoTargetInIdle\":false,\"Condition\":0,\"AICastCondition\":0,\"SkillEffectExecuteInfo\":{\"SelectConfigID\":0,\"SkillEffectConfigID\":0},\"SkillEffectPassiveExecuteInfo\":{\"SelectConfigID\":0,\"SkillEffectConfigID\":44000037},\"SkillEffectOnUnEquip\":0,\"ChantCounterValuesList\":[],\"LGDamageValuesList\":[],\"SkillDamageTagsList\":[],\"SkillTagsList\":[{\"SkillTagConfigID\":440005,\"Value\":0}],\"SkillTipsConditionSkillTagsList\":[],\"TalentKeyWord\":[],\"UseSkillSpeedDownValue\":0,\"UseSkillSpeedDownTime\":0,\"SkillIndicatorType\":0,\"SkillIndicatorParam\":[],\"SkillIndicatorParamTagConfigIds\":[],\"SkillIndicatorResParam\":[],\"SkillIndicatorResParamTagConfigIds\":[],\"LockEntityAfterUseSkillDuration\":0,\"LockEntityPosTypeAfterUseSkill\":0,\"SkillEffectOnSkillCastInterrupt\":0,\"UseSkillForbidUpdateFaceDir\":false,\"UseType\":0,\"ButtonUpConfig\":0,\"InterruptConfig\":0,\"ReActiveConfig\":0,\"SkillQuality\":0,\"IsPassiveSkillHideCD\":false,\"IsPassiveSkillNotRunByCD\":false,\"SkillProperty\":0,\"SkillRangeTagConfigId\":0,\"SkillMinRangeTagConfigId\":0,\"SmartCastTargetBasePriority\":0,\"SmartCastTargetCondTemplate\":0,\"SmartCastTargetMonsterRankCond\":[],\"SmartCastTargetCampCond\":[],\"SmartCastNoTargetIndicatorPos\":0,\"SmartCastNoTargetCancelUse\":false,\"CastTargetCondTemplate\":0,\"CastTargetMonsterRankCond\":[],\"CastTargetCampCond\":[],\"IsHideContinueUseSkillHeadBar\":false,\"SkillPriority\":0,\"EnhanceSkillBuffConfigID\":0,\"StatisticsDamageAloneForSummon\":false,\"SkillNameEditor\":\"鸿都秘术\",\"SkillDescEditor\":\"对修士类的敌人，伤害增加5%/10%/15%/20%/25%。\"}",
                    "Config2ID": "SkillConfig_400002"
                }
            },
            {
                "rid": 1001,
                "type": {
                    "class": "TSET_ORDER_EXECUTE",
                    "ns": "NodeEditor",
                    "asm": "NodeEditor"
                },
                "data": {
                    "GUID": "e358e457-e288-4209-91cf-3f6216fa17aa",
                    "computeOrder": 1,
                    "position": {
                        "serializedVersion": "2",
                        "x": 793.0,
                        "y": 296.0,
                        "width": 260.0,
                        "height": 95.0
                    },
                    "expanded": false,
                    "debug": false,
                    "nodeLock": false,
                    "visible": true,
                    "hideChildNodes": false,
                    "hidePos": {
                        "x": 0.0,
                        "y": 0.0
                    },
                    "hideCounter": 0,
                    "ID": 44000037,
                    "Desc": "",
                    "IsTemplate": false,
                    "TemplateFlags": 0,
                    "TemplateParams": [],
                    "TemplateParamsDesc": [],
                    "TemplateParamsCustomAdd": false,
                    "TableTash": "0CFA05568A66FEA1DF3BA6FE40DB7080",
                    "ConfigJson": "{\"ID\":44000037,\"SkillEffectType\":1,\"Params\":[{\"Value\":44000047,\"ParamType\":0,\"Factor\":0},{\"Value\":23000049,\"ParamType\":0,\"Factor\":0}]}",
                    "Config2ID": "SkillEffectConfig_44000037",
                    "SkillEffectType": 1
                }
            },
            {
                "rid": 1002,
                "type": {
                    "class": "TSET_REGISTER_SKILL_EVENT",
                    "ns": "NodeEditor",
                    "asm": "NodeEditor"
                },
                "data": {
                    "GUID": "342f3264-fb8f-47eb-a07b-13a054e615f1",
                    "computeOrder": 2,
                    "position": {
                        "serializedVersion": "2",
                        "x": 1130.1304931640625,
                        "y": 297.0,
                        "width": 314.0,
                        "height": 335.0
                    },
                    "expanded": false,
                    "debug": false,
                    "nodeLock": false,
                    "visible": true,
                    "hideChildNodes": false,
                    "hidePos": {
                        "x": 0.0,
                        "y": 0.0
                    },
                    "hideCounter": 0,
                    "ID": 44000047,
                    "Desc": "",
                    "IsTemplate": false,
                    "TemplateFlags": 0,
                    "TemplateParams": [],
                    "TemplateParamsDesc": [],
                    "TemplateParamsCustomAdd": false,
                    "TableTash": "0CFA05568A66FEA1DF3BA6FE40DB7080",
                    "ConfigJson": "{\"ID\":44000047,\"SkillEffectType\":68,\"Params\":[{\"Value\":15,\"ParamType\":0,\"Factor\":0},{\"Value\":44000032,\"ParamType\":0,\"Factor\":0},{\"Value\":0,\"ParamType\":0,\"Factor\":0},{\"Value\":0,\"ParamType\":0,\"Factor\":0},{\"Value\":440003,\"ParamType\":0,\"Factor\":0},{\"Value\":-1,\"ParamType\":0,\"Factor\":0},{\"Value\":0,\"ParamType\":0,\"Factor\":0},{\"Value\":0,\"ParamType\":0,\"Factor\":0},{\"Value\":0,\"ParamType\":0,\"Factor\":0},{\"Value\":0,\"ParamType\":0,\"Factor\":0},{\"Value\":0,\"ParamType\":0,\"Factor\":0}]}",
                    "Config2ID": "SkillEffectConfig_44000047",
                    "SkillEffectType": 68
                }
            },
            {
                "rid": 1003,
                "type": {
                    "class": "TSET_ADD_ENTITY_ATTR_VALUE",
                    "ns": "NodeEditor",
                    "asm": "NodeEditor"
                },
                "data": {
                    "GUID": "f34d7ed3-01ed-4010-9add-073d28727575",
                    "computeOrder": 4,
                    "position": {
                        "serializedVersion": "2",
                        "x": 1809.800048828125,
                        "y": -277.5740051269531,
                        "width": 304.0,
                        "height": 143.00003051757813
                    },
                    "expanded": false,
                    "debug": false,
                    "nodeLock": false,
                    "visible": true,
                    "hideChildNodes": false,
                    "hidePos": {
                        "x": 0.0,
                        "y": 0.0
                    },
                    "hideCounter": 0,
                    "ID": 44000048,
                    "Desc": "",
                    "IsTemplate": false,
                    "TemplateFlags": 0,
                    "TemplateParams": [],
                    "TemplateParamsDesc": [],
                    "TemplateParamsCustomAdd": false,
                    "TableTash": "0CFA05568A66FEA1DF3BA6FE40DB7080",
                    "ConfigJson": "{\"ID\":44000048,\"SkillEffectType\":71,\"Params\":[{\"Value\":75,\"ParamType\":1,\"Factor\":0},{\"Value\":53,\"ParamType\":0,\"Factor\":0},{\"Value\":44000027,\"ParamType\":2,\"Factor\":0}]}",
                    "Config2ID": "SkillEffectConfig_44000048",
                    "SkillEffectType": 71
                }
            },
            {
                "rid": 1004,
                "type": {
                    "class": "TSCT_AND",
                    "ns": "NodeEditor",
                    "asm": "NodeEditor"
                },
                "data": {
                    "GUID": "05b1c01e-35a7-4385-9b44-0e44a7f5ef98",
                    "computeOrder": 5,
                    "position": {
                        "serializedVersion": "2",
                        "x": 1493.0,
                        "y": 761.0,
                        "width": 254.0,
                        "height": 95.0
                    },
                    "expanded": false,
                    "debug": false,
                    "nodeLock": false,
                    "visible": true,
                    "hideChildNodes": false,
                    "hidePos": {
                        "x": 0.0,
                        "y": 0.0
                    },
                    "hideCounter": 0,
                    "ID": 440003,
                    "Desc": "",
                    "IsTemplate": false,
                    "TemplateFlags": 0,
                    "TemplateParams": [],
                    "TemplateParamsDesc": [],
                    "TemplateParamsCustomAdd": false,
                    "TableTash": "ED89F46EAB95F7ACF5C1911A5A375278",
                    "ConfigJson": "{\"ID\":440003,\"SkillConditionType\":1,\"Params\":[{\"Value\":440009,\"ParamType\":0,\"Factor\":0},{\"Value\":440016,\"ParamType\":0,\"Factor\":0}]}",
                    "Config2ID": "SkillConditionConfig_440003",
                    "SkillConditionType": 1
                }
            },
            {
                "rid": 1005,
                "type": {
                    "class": "TSET_GET_SKILL_TAG_VALUE",
                    "ns": "NodeEditor",
                    "asm": "NodeEditor"
                },
                "data": {
                    "GUID": "e3646843-cc08-4ba4-8cd8-dee5a1b70c98",
                    "computeOrder": 6,
                    "position": {
                        "serializedVersion": "2",
                        "x": 2219.800048828125,
                        "y": -231.5740203857422,
                        "width": 380.000244140625,
                        "height": 191.00003051757813
                    },
                    "expanded": false,
                    "debug": false,
                    "nodeLock": false,
                    "visible": true,
                    "hideChildNodes": false,
                    "hidePos": {
                        "x": 0.0,
                        "y": 0.0
                    },
                    "hideCounter": 0,
                    "ID": 44000027,
                    "Desc": "",
                    "IsTemplate": false,
                    "TemplateFlags": 0,
                    "TemplateParams": [],
                    "TemplateParamsDesc": [],
                    "TemplateParamsCustomAdd": false,
                    "TableTash": "0CFA05568A66FEA1DF3BA6FE40DB7080",
                    "ConfigJson": "{\"ID\":44000027,\"SkillEffectType\":48,\"Params\":[{\"Value\":4,\"ParamType\":5,\"Factor\":0},{\"Value\":7,\"ParamType\":5,\"Factor\":0},{\"Value\":440005,\"ParamType\":0,\"Factor\":0},{\"Value\":1,\"ParamType\":0,\"Factor\":0},{\"Value\":1,\"ParamType\":0,\"Factor\":0}]}",
                    "Config2ID": "SkillEffectConfig_44000027",
                    "SkillEffectType": 48
                }
            },
            {
                "rid": 1006,
                "type": {
                    "class": "SkillTagsConfigNode",
                    "ns": "NodeEditor",
                    "asm": "NodeEditor"
                },
                "data": {
                    "GUID": "baf032c0-3de6-4af9-9614-861804b07c5e",
                    "computeOrder": 7,
                    "position": {
                        "serializedVersion": "2",
                        "x": 886.8978271484375,
                        "y": -585.4990844726563,
                        "width": 238.0,
                        "height": 95.0
                    },
                    "expanded": false,
                    "debug": false,
                    "nodeLock": false,
                    "visible": true,
                    "hideChildNodes": false,
                    "hidePos": {
                        "x": 0.0,
                        "y": 0.0
                    },
                    "hideCounter": 0,
                    "ID": 440005,
                    "Desc": "",
                    "IsTemplate": false,
                    "TemplateFlags": 0,
                    "TemplateParams": [],
                    "TemplateParamsDesc": [],
                    "TemplateParamsCustomAdd": false,
                    "TableTash": "6A8A6883BDFDA1411BB2461E65CB2D9B",
                    "ConfigJson": "{\"ID\":440005,\"TagType\":3,\"Desc\":\"真诀鸿都伤害比例\",\"NameKey\":0,\"DefaultValue\":0,\"FinalValueEffectID\":23000052,\"RetainWhenDie\":false,\"NameEditor\":\"真诀鸿都伤害比例\"}",
                    "Config2ID": "SkillTagsConfig_440005"
                }
            },
            {
                "rid": 1007,
                "type": {
                    "class": "TSCT_VALUE_COMPARE",
                    "ns": "NodeEditor",
                    "asm": "NodeEditor"
                },
                "data": {
                    "GUID": "ee0cc5ee-8b7b-4e43-b68b-f07af5628f0f",
                    "computeOrder": 8,
                    "position": {
                        "serializedVersion": "2",
                        "x": 1838.0,
                        "y": 568.0,
                        "width": 302.0,
                        "height": 143.0
                    },
                    "expanded": false,
                    "debug": false,
                    "nodeLock": false,
                    "visible": true,
                    "hideChildNodes": false,
                    "hidePos": {
                        "x": 0.0,
                        "y": 0.0
                    },
                    "hideCounter": 0,
                    "ID": 440009,
                    "Desc": "",
                    "IsTemplate": false,
                    "TemplateFlags": 0,
                    "TemplateParams": [],
                    "TemplateParamsDesc": [],
                    "TemplateParamsCustomAdd": false,
                    "TableTash": "ED89F46EAB95F7ACF5C1911A5A375278",
                    "ConfigJson": "{\"ID\":440009,\"SkillConditionType\":7,\"Params\":[{\"Value\":75,\"ParamType\":1,\"Factor\":0},{\"Value\":1,\"ParamType\":0,\"Factor\":0},{\"Value\":1,\"ParamType\":6,\"Factor\":0}]}",
                    "Config2ID": "SkillConditionConfig_440009",
                    "SkillConditionType": 7
                }
            },
            {
                "rid": 1008,
                "type": {
                    "class": "TSCT_ENTITY_RACE_TYPE",
                    "ns": "NodeEditor",
                    "asm": "NodeEditor"
                },
                "data": {
                    "GUID": "1c25095d-8311-4337-ae2d-0103356239bb",
                    "computeOrder": 10,
                    "position": {
                        "serializedVersion": "2",
                        "x": 2192.0,
                        "y": 827.0,
                        "width": 353.0,
                        "height": 119.0
                    },
                    "expanded": false,
                    "debug": false,
                    "nodeLock": false,
                    "visible": true,
                    "hideChildNodes": false,
                    "hidePos": {
                        "x": 0.0,
                        "y": 0.0
                    },
                    "hideCounter": 0,
                    "ID": 440010,
                    "Desc": "",
                    "IsTemplate": false,
                    "TemplateFlags": 0,
                    "TemplateParams": [],
                    "TemplateParamsDesc": [],
                    "TemplateParamsCustomAdd": false,
                    "TableTash": "ED89F46EAB95F7ACF5C1911A5A375278",
                    "ConfigJson": "{\"ID\":440010,\"SkillConditionType\":39,\"Params\":[{\"Value\":2,\"ParamType\":6,\"Factor\":0},{\"Value\":1,\"ParamType\":0,\"Factor\":0}]}",
                    "Config2ID": "SkillConditionConfig_440010",
                    "SkillConditionType": 39
                }
            },
            {
                "rid": 1009,
                "type": {
                    "class": "TSET_REGISTER_SKILL_EVENT",
                    "ns": "NodeEditor",
                    "asm": "NodeEditor"
                },
                "data": {
                    "GUID": "94189406-a2af-4783-aa47-dc9fa23be3bb",
                    "computeOrder": 11,
                    "position": {
                        "serializedVersion": "2",
                        "x": 1831.8734130859375,
                        "y": 4.358860492706299,
                        "width": 355.9998779296875,
                        "height": 335.0000305175781
                    },
                    "expanded": false,
                    "debug": false,
                    "nodeLock": false,
                    "visible": true,
                    "hideChildNodes": false,
                    "hidePos": {
                        "x": 0.0,
                        "y": 0.0
                    },
                    "hideCounter": 0,
                    "ID": 44000028,
                    "Desc": "",
                    "IsTemplate": false,
                    "TemplateFlags": 0,
                    "TemplateParams": [],
                    "TemplateParamsDesc": [],
                    "TemplateParamsCustomAdd": false,
                    "TableTash": "0CFA05568A66FEA1DF3BA6FE40DB7080",
                    "ConfigJson": "{\"ID\":44000028,\"SkillEffectType\":68,\"Params\":[{\"Value\":11,\"ParamType\":0,\"Factor\":0},{\"Value\":44000029,\"ParamType\":0,\"Factor\":0},{\"Value\":0,\"ParamType\":0,\"Factor\":0},{\"Value\":0,\"ParamType\":0,\"Factor\":0},{\"Value\":440011,\"ParamType\":0,\"Factor\":0},{\"Value\":1,\"ParamType\":0,\"Factor\":0},{\"Value\":0,\"ParamType\":0,\"Factor\":0},{\"Value\":0,\"ParamType\":0,\"Factor\":0},{\"Value\":0,\"ParamType\":0,\"Factor\":0},{\"Value\":0,\"ParamType\":0,\"Factor\":0},{\"Value\":0,\"ParamType\":0,\"Factor\":0}]}",
                    "Config2ID": "SkillEffectConfig_44000028",
                    "SkillEffectType": 68
                }
            },
            {
                "rid": 1010,
                "type": {
                    "class": "TSET_ADD_ENTITY_ATTR_VALUE",
                    "ns": "NodeEditor",
                    "asm": "NodeEditor"
                },
                "data": {
                    "GUID": "19a6feac-1806-46b2-ae4a-bd2f8e160626",
                    "computeOrder": 12,
                    "position": {
                        "serializedVersion": "2",
                        "x": 2291.873291015625,
                        "y": -19.64114761352539,
                        "width": 303.0,
                        "height": 143.00003051757813
                    },
                    "expanded": false,
                    "debug": false,
                    "nodeLock": false,
                    "visible": true,
                    "hideChildNodes": false,
                    "hidePos": {
                        "x": 0.0,
                        "y": 0.0
                    },
                    "hideCounter": 0,
                    "ID": 44000029,
                    "Desc": "",
                    "IsTemplate": false,
                    "TemplateFlags": 0,
                    "TemplateParams": [],
                    "TemplateParamsDesc": [],
                    "TemplateParamsCustomAdd": false,
                    "TableTash": "0CFA05568A66FEA1DF3BA6FE40DB7080",
                    "ConfigJson": "{\"ID\":44000029,\"SkillEffectType\":71,\"Params\":[{\"Value\":75,\"ParamType\":1,\"Factor\":0},{\"Value\":53,\"ParamType\":0,\"Factor\":0},{\"Value\":44000030,\"ParamType\":2,\"Factor\":0}]}",
                    "Config2ID": "SkillEffectConfig_44000029",
                    "SkillEffectType": 71
                }
            },
            {
                "rid": 1011,
                "type": {
                    "class": "TSCT_AND",
                    "ns": "NodeEditor",
                    "asm": "NodeEditor"
                },
                "data": {
                    "GUID": "4d860b7f-5410-4333-850c-dde8b1c5c5b4",
                    "computeOrder": 13,
                    "position": {
                        "serializedVersion": "2",
                        "x": 2292.0,
                        "y": 217.16822814941407,
                        "width": 250.0,
                        "height": 94.99998474121094
                    },
                    "expanded": false,
                    "debug": false,
                    "nodeLock": false,
                    "visible": true,
                    "hideChildNodes": false,
                    "hidePos": {
                        "x": 0.0,
                        "y": 0.0
                    },
                    "hideCounter": 0,
                    "ID": 440011,
                    "Desc": "",
                    "IsTemplate": false,
                    "TemplateFlags": 0,
                    "TemplateParams": [],
                    "TemplateParamsDesc": [],
                    "TemplateParamsCustomAdd": false,
                    "TableTash": "ED89F46EAB95F7ACF5C1911A5A375278",
                    "ConfigJson": "{\"ID\":440011,\"SkillConditionType\":1,\"Params\":[{\"Value\":440012,\"ParamType\":0,\"Factor\":0},{\"Value\":440025,\"ParamType\":0,\"Factor\":0}]}",
                    "Config2ID": "SkillConditionConfig_440011",
                    "SkillConditionType": 1
                }
            },
            {
                "rid": 1012,
                "type": {
                    "class": "TSCT_VALUE_COMPARE",
                    "ns": "NodeEditor",
                    "asm": "NodeEditor"
                },
                "data": {
                    "GUID": "3cf70409-dbb7-4690-ac45-7aa843e2ea54",
                    "computeOrder": 14,
                    "position": {
                        "serializedVersion": "2",
                        "x": 2646.900390625,
                        "y": 235.64999389648438,
                        "width": 299.999755859375,
                        "height": 143.00006103515626
                    },
                    "expanded": false,
                    "debug": false,
                    "nodeLock": false,
                    "visible": true,
                    "hideChildNodes": false,
                    "hidePos": {
                        "x": 0.0,
                        "y": 0.0
                    },
                    "hideCounter": 0,
                    "ID": 440012,
                    "Desc": "",
                    "IsTemplate": false,
                    "TemplateFlags": 0,
                    "TemplateParams": [],
                    "TemplateParamsDesc": [],
                    "TemplateParamsCustomAdd": false,
                    "TableTash": "ED89F46EAB95F7ACF5C1911A5A375278",
                    "ConfigJson": "{\"ID\":440012,\"SkillConditionType\":7,\"Params\":[{\"Value\":75,\"ParamType\":1,\"Factor\":0},{\"Value\":1,\"ParamType\":0,\"Factor\":0},{\"Value\":1,\"ParamType\":6,\"Factor\":0}]}",
                    "Config2ID": "SkillConditionConfig_440012",
                    "SkillConditionType": 7
                }
            },
            {
                "rid": 1013,
                "type": {
                    "class": "TSCT_ENTITY_RACE_TYPE",
                    "ns": "NodeEditor",
                    "asm": "NodeEditor"
                },
                "data": {
                    "GUID": "ab0952c2-cbf6-40ce-8128-568db3b69b1b",
                    "computeOrder": 16,
                    "position": {
                        "serializedVersion": "2",
                        "x": 2967.86962890625,
                        "y": 532.0,
                        "width": 353.0,
                        "height": 119.0
                    },
                    "expanded": false,
                    "debug": false,
                    "nodeLock": false,
                    "visible": true,
                    "hideChildNodes": false,
                    "hidePos": {
                        "x": 0.0,
                        "y": 0.0
                    },
                    "hideCounter": 0,
                    "ID": 440013,
                    "Desc": "",
                    "IsTemplate": false,
                    "TemplateFlags": 0,
                    "TemplateParams": [],
                    "TemplateParamsDesc": [],
                    "TemplateParamsCustomAdd": false,
                    "TableTash": "ED89F46EAB95F7ACF5C1911A5A375278",
                    "ConfigJson": "{\"ID\":440013,\"SkillConditionType\":39,\"Params\":[{\"Value\":2,\"ParamType\":6,\"Factor\":0},{\"Value\":1,\"ParamType\":0,\"Factor\":0}]}",
                    "Config2ID": "SkillConditionConfig_440013",
                    "SkillConditionType": 39
                }
            },
            {
                "rid": 1014,
                "type": {
                    "class": "TSET_NUM_CALCULATE",
                    "ns": "NodeEditor",
                    "asm": "NodeEditor"
                },
                "data": {
                    "GUID": "9b5fdd87-8c63-4bee-9ff5-56ab7e54cc81",
                    "computeOrder": 17,
                    "position": {
                        "serializedVersion": "2",
                        "x": 2629.873291015625,
                        "y": 90.35890197753906,
                        "width": 260.000244140625,
                        "height": 142.99993896484376
                    },
                    "expanded": false,
                    "debug": false,
                    "nodeLock": false,
                    "visible": true,
                    "hideChildNodes": false,
                    "hidePos": {
                        "x": 0.0,
                        "y": 0.0
                    },
                    "hideCounter": 0,
                    "ID": 44000030,
                    "Desc": "",
                    "IsTemplate": false,
                    "TemplateFlags": 0,
                    "TemplateParams": [],
                    "TemplateParamsDesc": [],
                    "TemplateParamsCustomAdd": false,
                    "TableTash": "0CFA05568A66FEA1DF3BA6FE40DB7080",
                    "ConfigJson": "{\"ID\":44000030,\"SkillEffectType\":31,\"Params\":[{\"Value\":44000031,\"ParamType\":2,\"Factor\":0},{\"Value\":5,\"ParamType\":0,\"Factor\":0},{\"Value\":-1,\"ParamType\":0,\"Factor\":0}]}",
                    "Config2ID": "SkillEffectConfig_44000030",
                    "SkillEffectType": 31
                }
            },
            {
                "rid": 1015,
                "type": {
                    "class": "TSET_GET_SKILL_TAG_VALUE",
                    "ns": "NodeEditor",
                    "asm": "NodeEditor"
                },
                "data": {
                    "GUID": "32ad969a-9c48-4bbd-a6c2-cb9ea132ef50",
                    "computeOrder": 18,
                    "position": {
                        "serializedVersion": "2",
                        "x": 2993.87353515625,
                        "y": 99.35887145996094,
                        "width": 378.999755859375,
                        "height": 191.0000457763672
                    },
                    "expanded": false,
                    "debug": false,
                    "nodeLock": false,
                    "visible": true,
                    "hideChildNodes": false,
                    "hidePos": {
                        "x": 0.0,
                        "y": 0.0
                    },
                    "hideCounter": 0,
                    "ID": 44000031,
                    "Desc": "",
                    "IsTemplate": false,
                    "TemplateFlags": 0,
                    "TemplateParams": [],
                    "TemplateParamsDesc": [],
                    "TemplateParamsCustomAdd": false,
                    "TableTash": "0CFA05568A66FEA1DF3BA6FE40DB7080",
                    "ConfigJson": "{\"ID\":44000031,\"SkillEffectType\":48,\"Params\":[{\"Value\":4,\"ParamType\":5,\"Factor\":0},{\"Value\":7,\"ParamType\":5,\"Factor\":0},{\"Value\":440005,\"ParamType\":0,\"Factor\":0},{\"Value\":1,\"ParamType\":0,\"Factor\":0},{\"Value\":1,\"ParamType\":0,\"Factor\":0}]}",
                    "Config2ID": "SkillEffectConfig_44000031",
                    "SkillEffectType": 48
                }
            },
            {
                "rid": 1016,
                "type": {
                    "class": "TSCT_OR",
                    "ns": "NodeEditor",
                    "asm": "NodeEditor"
                },
                "data": {
                    "GUID": "a8df796d-8050-4675-8e48-dd90c525744e",
                    "computeOrder": 9,
                    "position": {
                        "serializedVersion": "2",
                        "x": 1842.0,
                        "y": 822.0,
                        "width": 252.0,
                        "height": 95.0
                    },
                    "expanded": false,
                    "debug": false,
                    "nodeLock": false,
                    "visible": true,
                    "hideChildNodes": false,
                    "hidePos": {
                        "x": 0.0,
                        "y": 0.0
                    },
                    "hideCounter": 0,
                    "ID": 440016,
                    "Desc": "",
                    "IsTemplate": false,
                    "TemplateFlags": 0,
                    "TemplateParams": [],
                    "TemplateParamsDesc": [],
                    "TemplateParamsCustomAdd": false,
                    "TableTash": "ED89F46EAB95F7ACF5C1911A5A375278",
                    "ConfigJson": "{\"ID\":440016,\"SkillConditionType\":2,\"Params\":[{\"Value\":440010,\"ParamType\":0,\"Factor\":0}]}",
                    "Config2ID": "SkillConditionConfig_440016",
                    "SkillConditionType": 2
                }
            },
            {
                "rid": 1017,
                "type": {
                    "class": "TSCT_OR",
                    "ns": "NodeEditor",
                    "asm": "NodeEditor"
                },
                "data": {
                    "GUID": "720055a5-7f2d-426c-b185-37d05070feda",
                    "computeOrder": 15,
                    "position": {
                        "serializedVersion": "2",
                        "x": 2648.050537109375,
                        "y": 420.6500244140625,
                        "width": 253.999755859375,
                        "height": 95.0
                    },
                    "expanded": false,
                    "debug": false,
                    "nodeLock": false,
                    "visible": true,
                    "hideChildNodes": false,
                    "hidePos": {
                        "x": 0.0,
                        "y": 0.0
                    },
                    "hideCounter": 0,
                    "ID": 440025,
                    "Desc": "",
                    "IsTemplate": false,
                    "TemplateFlags": 0,
                    "TemplateParams": [],
                    "TemplateParamsDesc": [],
                    "TemplateParamsCustomAdd": false,
                    "TableTash": "ED89F46EAB95F7ACF5C1911A5A375278",
                    "ConfigJson": "{\"ID\":440025,\"SkillConditionType\":2,\"Params\":[{\"Value\":440013,\"ParamType\":0,\"Factor\":0}]}",
                    "Config2ID": "SkillConditionConfig_440025",
                    "SkillConditionType": 2
                }
            },
            {
                "rid": 1018,
                "type": {
                    "class": "TSET_ORDER_EXECUTE",
                    "ns": "NodeEditor",
                    "asm": "NodeEditor"
                },
                "data": {
                    "GUID": "c57a169c-50fc-4779-aac2-e429890b6eed",
                    "computeOrder": 3,
                    "position": {
                        "serializedVersion": "2",
                        "x": 1499.0,
                        "y": 15.0,
                        "width": 100.0,
                        "height": 100.0
                    },
                    "expanded": false,
                    "debug": false,
                    "nodeLock": false,
                    "visible": true,
                    "hideChildNodes": false,
                    "hidePos": {
                        "x": 0.0,
                        "y": 0.0
                    },
                    "hideCounter": 0,
                    "ID": 44000032,
                    "Desc": "",
                    "IsTemplate": false,
                    "TemplateFlags": 0,
                    "TemplateParams": [],
                    "TemplateParamsDesc": [],
                    "TemplateParamsCustomAdd": false,
                    "TableTash": "0CFA05568A66FEA1DF3BA6FE40DB7080",
                    "ConfigJson": "{\"ID\":44000032,\"SkillEffectType\":1,\"Params\":[{\"Value\":44000048,\"ParamType\":0,\"Factor\":0},{\"Value\":44000028,\"ParamType\":0,\"Factor\":0}]}",
                    "Config2ID": "SkillEffectConfig_44000032",
                    "SkillEffectType": 1
                }
            },
            {
                "rid": 1019,
                "type": {
                    "class": "RefConfigBaseNode",
                    "ns": "NodeEditor",
                    "asm": "NodeEditor"
                },
                "data": {
                    "GUID": "174780ca-2d03-4cf4-839e-8fd358332389",
                    "computeOrder": 19,
                    "position": {
                        "serializedVersion": "2",
                        "x": 1128.0,
                        "y": 671.0,
                        "width": 352.0,
                        "height": 95.0
                    },
                    "expanded": false,
                    "debug": false,
                    "nodeLock": false,
                    "visible": true,
                    "hideChildNodes": false,
                    "hidePos": {
                        "x": 0.0,
                        "y": 0.0
                    },
                    "hideCounter": 0,
                    "TableManagerName": "TableDR.SkillEffectConfigManager",
                    "ID": 23000049,
                    "ManualID": 23000049
                }
            }
        ]
    }
}