{
    "serializationData": {
        "SerializedFormat": 0,
        "SerializedBytes": [],
        "ReferencedUnityObjects": [],
        "SerializedBytesString": "",
        "Prefab": {
            "instanceID": 0
        },
        "PrefabModificationsReferencedUnityObjects": [],
        "PrefabModifications": [],
        "SerializationNodes": []
    },
    "nodes": [
        {
            "rid": 1000
        },
        {
            "rid": 1001
        },
        {
            "rid": 1002
        },
        {
            "rid": 1003
        },
        {
            "rid": 1004
        },
        {
            "rid": 1005
        },
        {
            "rid": 1006
        },
        {
            "rid": 1007
        },
        {
            "rid": 1008
        },
        {
            "rid": 1009
        },
        {
            "rid": 1010
        },
        {
            "rid": 1011
        },
        {
            "rid": 1012
        },
        {
            "rid": 1013
        },
        {
            "rid": 1014
        },
        {
            "rid": 1015
        },
        {
            "rid": 1016
        },
        {
            "rid": 1017
        },
        {
            "rid": 1018
        },
        {
            "rid": 1019
        },
        {
            "rid": 1020
        },
        {
            "rid": 1021
        },
        {
            "rid": 1022
        },
        {
            "rid": 1023
        },
        {
            "rid": 1024
        },
        {
            "rid": 1025
        },
        {
            "rid": 1026
        },
        {
            "rid": 1027
        },
        {
            "rid": 1028
        }
    ],
    "edges": [
        {
            "GUID": "c353cfe9-3f09-499a-b264-7dce9a0acbef",
            "inputNodeGUID": "79af6a7f-fd86-4437-8f2a-96c564eeba75",
            "outputNodeGUID": "56c61636-9f41-47bc-9f4b-f0129f0cabaa",
            "inputFieldName": "ID",
            "outputFieldName": "PackedMembersOutput",
            "inputPortIdentifier": "0",
            "outputPortIdentifier": "SkillEffectPassiveExecuteInfo.SkillEffectConfigID",
            "isVisible": true
        },
        {
            "GUID": "4b5d0d03-8f4c-4d67-94ec-dedc556b3d1f",
            "inputNodeGUID": "eb3a010d-1db0-44fb-a2d6-d2b399b5dad9",
            "outputNodeGUID": "79af6a7f-fd86-4437-8f2a-96c564eeba75",
            "inputFieldName": "ID",
            "outputFieldName": "PackedParamsOutput",
            "inputPortIdentifier": "0",
            "outputPortIdentifier": "0",
            "isVisible": true
        },
        {
            "GUID": "c5c5f093-762d-415e-b88d-e74e2078939c",
            "inputNodeGUID": "a36e6ff6-62e0-4baf-abcc-9fe624224ecd",
            "outputNodeGUID": "eb3a010d-1db0-44fb-a2d6-d2b399b5dad9",
            "inputFieldName": "ID",
            "outputFieldName": "PackedParamsOutput",
            "inputPortIdentifier": "0",
            "outputPortIdentifier": "1",
            "isVisible": true
        },
        {
            "GUID": "9d7674f4-68e1-4aa4-aa7b-0eec0f314a6c",
            "inputNodeGUID": "7bbad3f7-e748-4f43-9559-5e2cc4cc6e54",
            "outputNodeGUID": "68e56963-d0b9-4d73-b1a8-c320a5b29420",
            "inputFieldName": "ID",
            "outputFieldName": "PackedParamsOutput",
            "inputPortIdentifier": "0",
            "outputPortIdentifier": "0",
            "isVisible": true
        },
        {
            "GUID": "2dcf6195-e611-4a09-be29-62efeff59e2e",
            "inputNodeGUID": "62f9de12-b84c-4ddb-be6f-8108606d01f6",
            "outputNodeGUID": "7bbad3f7-e748-4f43-9559-5e2cc4cc6e54",
            "inputFieldName": "ID",
            "outputFieldName": "PackedParamsOutput",
            "inputPortIdentifier": "0",
            "outputPortIdentifier": "0",
            "isVisible": true
        },
        {
            "GUID": "692e12bb-b276-4a00-b8ce-83ae797f5abb",
            "inputNodeGUID": "1f4a3cd6-aaa2-44fe-ba7c-30c5c2c1ee75",
            "outputNodeGUID": "a36e6ff6-62e0-4baf-abcc-9fe624224ecd",
            "inputFieldName": "ID",
            "outputFieldName": "PackedParamsOutput",
            "inputPortIdentifier": "0",
            "outputPortIdentifier": "0",
            "isVisible": true
        },
        {
            "GUID": "3da7cf34-aead-40f1-9f23-b13e387b3d1c",
            "inputNodeGUID": "68e56963-d0b9-4d73-b1a8-c320a5b29420",
            "outputNodeGUID": "a36e6ff6-62e0-4baf-abcc-9fe624224ecd",
            "inputFieldName": "ID",
            "outputFieldName": "PackedParamsOutput",
            "inputPortIdentifier": "0",
            "outputPortIdentifier": "0",
            "isVisible": true
        },
        {
            "GUID": "f0a47d7e-b991-4f83-8e3e-db4a4533f2ac",
            "inputNodeGUID": "de511fd5-56ae-407a-b55a-57cb02033a5f",
            "outputNodeGUID": "68e56963-d0b9-4d73-b1a8-c320a5b29420",
            "inputFieldName": "ID",
            "outputFieldName": "PackedParamsOutput",
            "inputPortIdentifier": "0",
            "outputPortIdentifier": "1",
            "isVisible": true
        },
        {
            "GUID": "0ba2c24a-d0a8-4a4a-a37e-e8a9f0b60361",
            "inputNodeGUID": "2b5fa0fa-2b5d-4d95-a3fd-28a9830b925a",
            "outputNodeGUID": "de511fd5-56ae-407a-b55a-57cb02033a5f",
            "inputFieldName": "ID",
            "outputFieldName": "PackedParamsOutput",
            "inputPortIdentifier": "0",
            "outputPortIdentifier": "0",
            "isVisible": true
        },
        {
            "GUID": "96f0c060-b1b8-4282-a665-8eafdeb99a45",
            "inputNodeGUID": "35f9fcc6-bc26-44c3-90ca-91c48e34d31e",
            "outputNodeGUID": "de511fd5-56ae-407a-b55a-57cb02033a5f",
            "inputFieldName": "ID",
            "outputFieldName": "PackedParamsOutput",
            "inputPortIdentifier": "0",
            "outputPortIdentifier": "0",
            "isVisible": true
        },
        {
            "GUID": "df836d7d-a586-4657-a646-009dd29b5d09",
            "inputNodeGUID": "44fdc264-5260-4b97-97e8-42e59fe8a903",
            "outputNodeGUID": "2b5fa0fa-2b5d-4d95-a3fd-28a9830b925a",
            "inputFieldName": "ID",
            "outputFieldName": "PackedParamsOutput",
            "inputPortIdentifier": "0",
            "outputPortIdentifier": "2",
            "isVisible": true
        },
        {
            "GUID": "14c6db20-5af7-4aa7-b287-f8223016eb82",
            "inputNodeGUID": "de90292a-b4e4-4723-a2cc-f4b9ae903ac8",
            "outputNodeGUID": "de511fd5-56ae-407a-b55a-57cb02033a5f",
            "inputFieldName": "ID",
            "outputFieldName": "PackedParamsOutput",
            "inputPortIdentifier": "0",
            "outputPortIdentifier": "0",
            "isVisible": true
        },
        {
            "GUID": "35935a04-fb5e-492b-947e-65657e3e8b47",
            "inputNodeGUID": "eb2ef52a-0148-4ad7-97b3-92671e48b1da",
            "outputNodeGUID": "de90292a-b4e4-4723-a2cc-f4b9ae903ac8",
            "inputFieldName": "ID",
            "outputFieldName": "PackedParamsOutput",
            "inputPortIdentifier": "0",
            "outputPortIdentifier": "1",
            "isVisible": true
        },
        {
            "GUID": "6caca1bb-e827-4803-a989-80329be850e1",
            "inputNodeGUID": "90f3ef6c-aef5-42aa-a68e-9e2bab1a2ea6",
            "outputNodeGUID": "eb2ef52a-0148-4ad7-97b3-92671e48b1da",
            "inputFieldName": "ID",
            "outputFieldName": "PackedParamsOutput",
            "inputPortIdentifier": "0",
            "outputPortIdentifier": "0",
            "isVisible": true
        },
        {
            "GUID": "21e80db1-2654-425c-a0f9-90d725f4060d",
            "inputNodeGUID": "8a4ca4fa-a387-478f-a9e0-cb3ec3e9fc31",
            "outputNodeGUID": "eb3a010d-1db0-44fb-a2d6-d2b399b5dad9",
            "inputFieldName": "ID",
            "outputFieldName": "PackedParamsOutput",
            "inputPortIdentifier": "0",
            "outputPortIdentifier": "4",
            "isVisible": true
        },
        {
            "GUID": "e31cf2bd-6128-45f7-85d6-0f79e8885de0",
            "inputNodeGUID": "54416e0c-3ef5-4022-8753-48d895a20cde",
            "outputNodeGUID": "8a4ca4fa-a387-478f-a9e0-cb3ec3e9fc31",
            "inputFieldName": "ID",
            "outputFieldName": "PackedParamsOutput",
            "inputPortIdentifier": "0",
            "outputPortIdentifier": "0",
            "isVisible": true
        },
        {
            "GUID": "f8942640-6f8f-4957-865b-fc673e45f9d3",
            "inputNodeGUID": "b6a8df7a-5131-4f53-8beb-743c20436612",
            "outputNodeGUID": "44ab04cc-f422-410b-a78a-50981e7167fa",
            "inputFieldName": "ID",
            "outputFieldName": "PackedParamsOutput",
            "inputPortIdentifier": "0",
            "outputPortIdentifier": "0",
            "isVisible": true
        },
        {
            "GUID": "7fa60dfe-3931-4741-b8a9-a4270540ddc3",
            "inputNodeGUID": "acc17d7d-c286-4e97-9152-2bd9196fc997",
            "outputNodeGUID": "8726de9e-7513-4b20-8343-756f8bcf4417",
            "inputFieldName": "ID",
            "outputFieldName": "PackedParamsOutput",
            "inputPortIdentifier": "0",
            "outputPortIdentifier": "0",
            "isVisible": true
        },
        {
            "GUID": "018b511a-2e41-40c7-8534-a7b5968c6b68",
            "inputNodeGUID": "8726de9e-7513-4b20-8343-756f8bcf4417",
            "outputNodeGUID": "44ab04cc-f422-410b-a78a-50981e7167fa",
            "inputFieldName": "ID",
            "outputFieldName": "PackedParamsOutput",
            "inputPortIdentifier": "0",
            "outputPortIdentifier": "2",
            "isVisible": true
        },
        {
            "GUID": "607b2042-ee94-422d-a5ce-c1fea279e2cf",
            "inputNodeGUID": "52462c51-9f49-48c7-a843-cdf3bd0806e9",
            "outputNodeGUID": "8726de9e-7513-4b20-8343-756f8bcf4417",
            "inputFieldName": "ID",
            "outputFieldName": "PackedParamsOutput",
            "inputPortIdentifier": "0",
            "outputPortIdentifier": "4",
            "isVisible": true
        },
        {
            "GUID": "671bcbd8-48ca-45d0-a99e-13dcea7b3db4",
            "inputNodeGUID": "46a9423b-a29f-4a71-9241-dfd577dea193",
            "outputNodeGUID": "5439c5df-15f1-4e4a-9fe6-61c0206b73cb",
            "inputFieldName": "ID",
            "outputFieldName": "PackedParamsOutput",
            "inputPortIdentifier": "0",
            "outputPortIdentifier": "0",
            "isVisible": true
        },
        {
            "GUID": "53ed69a7-67b6-4da5-a3ff-e466d411fa48",
            "inputNodeGUID": "2fb69f21-8c97-4c35-85fb-6517bc4e2a1f",
            "outputNodeGUID": "9cd75ccd-f5c1-41c2-afed-87a470f89867",
            "inputFieldName": "ID",
            "outputFieldName": "PackedParamsOutput",
            "inputPortIdentifier": "0",
            "outputPortIdentifier": "0",
            "isVisible": true
        },
        {
            "GUID": "d55e0477-23a5-4250-95a6-7d32dfef3a5a",
            "inputNodeGUID": "9cd75ccd-f5c1-41c2-afed-87a470f89867",
            "outputNodeGUID": "5439c5df-15f1-4e4a-9fe6-61c0206b73cb",
            "inputFieldName": "ID",
            "outputFieldName": "PackedParamsOutput",
            "inputPortIdentifier": "0",
            "outputPortIdentifier": "2",
            "isVisible": true
        },
        {
            "GUID": "ce844da6-1e3b-47cd-b15d-c3a1d17d9f3a",
            "inputNodeGUID": "71bf71ea-e249-4b3e-bea5-af4d7b53f3ba",
            "outputNodeGUID": "9cd75ccd-f5c1-41c2-afed-87a470f89867",
            "inputFieldName": "ID",
            "outputFieldName": "PackedParamsOutput",
            "inputPortIdentifier": "0",
            "outputPortIdentifier": "4",
            "isVisible": true
        }
    ],
    "groups": [
        {
            "GUID": "5681a545-21aa-4151-b90a-0b986ce4eef5",
            "title": "器修增强",
            "color": {
                "r": 0.0,
                "g": 0.0,
                "b": 0.0,
                "a": 0.30000001192092898
            },
            "position": {
                "serializedVersion": "2",
                "x": 1220.0606689453125,
                "y": -1922.8004150390625,
                "width": 1196.0001220703125,
                "height": 1654.0001220703125
            },
            "size": {
                "x": 400.0,
                "y": 200.0
            },
            "innerNodeGUIDs": [
                "b6a8df7a-5131-4f53-8beb-743c20436612",
                "acc17d7d-c286-4e97-9152-2bd9196fc997",
                "8726de9e-7513-4b20-8343-756f8bcf4417",
                "52462c51-9f49-48c7-a843-cdf3bd0806e9",
                "44ab04cc-f422-410b-a78a-50981e7167fa",
                "46a9423b-a29f-4a71-9241-dfd577dea193",
                "2fb69f21-8c97-4c35-85fb-6517bc4e2a1f",
                "9cd75ccd-f5c1-41c2-afed-87a470f89867",
                "71bf71ea-e249-4b3e-bea5-af4d7b53f3ba",
                "5439c5df-15f1-4e4a-9fe6-61c0206b73cb"
            ],
            "innerStickyNoteGUIDs": []
        }
    ],
    "stackNodes": [],
    "pinnedElements": [
        {
            "position": {
                "serializedVersion": "2",
                "x": 0.0,
                "y": 0.0,
                "width": 355.0,
                "height": 282.0
            },
            "opened": true,
            "editorType": {
                "serializedType": "NodeEditor.ConfigPinnedView, NodeEditor, Version=0.0.0.0, Culture=neutral, PublicKeyToken=null"
            }
        }
    ],
    "exposedParameters": [],
    "serializedParameterList": [],
    "stickyNotes": [],
    "curTab": 4,
    "path": "Assets/Thirds/NodeEditor/SkillEditor/Saves/Jsons/法宝/SkillGraph_31031016【法宝被动】武器_塔.json",
    "references": {
        "version": 2,
        "RefIds": [
            {
                "rid": 1000,
                "type": {
                    "class": "SkillConfigNode",
                    "ns": "NodeEditor",
                    "asm": "NodeEditor"
                },
                "data": {
                    "GUID": "56c61636-9f41-47bc-9f4b-f0129f0cabaa",
                    "computeOrder": 0,
                    "position": {
                        "serializedVersion": "2",
                        "x": 0.0,
                        "y": 0.0,
                        "width": 100.0,
                        "height": 100.0
                    },
                    "expanded": false,
                    "debug": false,
                    "nodeLock": false,
                    "visible": true,
                    "hideChildNodes": false,
                    "hidePos": {
                        "x": 0.0,
                        "y": 0.0
                    },
                    "hideCounter": 0,
                    "ID": 31031016,
                    "Desc": "",
                    "IsTemplate": false,
                    "TemplateFlags": 0,
                    "TemplateParams": [],
                    "TemplateParamsDesc": [],
                    "TemplateParamsCustomAdd": false,
                    "TableTash": "0C2C5D4A7DC9280429315C2EEAD44FDF",
                    "ConfigJson": "{\"SkillXinfaType\":0,\"ID\":31031016,\"SkillNameKey\":3256601077,\"SkillDescKey\":2542607271,\"Icon\":\"\",\"ElementType\":0,\"SkillSchoolResType\":0,\"FeatureLabel\":0,\"BDLabels\":[],\"SkillAITags\":[],\"DamageType\":1,\"SkillMainType\":0,\"SkillSubType\":0,\"MPCost\":0,\"HunLiValue\":0,\"SectXinfaEnergyValue\":0,\"SkillCastFrame\":0,\"SkillBufferStartFrame\":0,\"SkillBufferFrame\":0,\"SkillBaseDuration\":0,\"SkillCastIsNotInterruptable\":false,\"IsSkillBufferFrameCanMove\":false,\"CdType\":0,\"CdTime\":0,\"ComboCdList\":[],\"CDMaxStoreCount\":0,\"SkillFixCdTime\":0,\"SkillRange\":0,\"SkillMinRange\":0,\"AISkillRange\":0,\"ExtraAlertRange\":0,\"IsCloseChaseInAlertRange\":false,\"NeedTargetInRange\":false,\"IsSkillCastNoTargetInIdle\":false,\"Condition\":0,\"AICastCondition\":0,\"SkillEffectExecuteInfo\":{\"SelectConfigID\":0,\"SkillEffectConfigID\":0},\"SkillEffectPassiveExecuteInfo\":{\"SelectConfigID\":0,\"SkillEffectConfigID\":220002474},\"SkillEffectOnUnEquip\":0,\"ChantCounterValuesList\":[],\"LGDamageValuesList\":[],\"SkillDamageTagsList\":[],\"SkillTagsList\":[{\"SkillTagConfigID\":2200079,\"Value\":2000},{\"SkillTagConfigID\":2200079,\"Value\":2000}],\"SkillTipsConditionSkillTagsList\":[],\"SkillGrowthDesc\":\"\",\"TalentKeyWord\":[],\"UseSkillSpeedDownValue\":0,\"UseSkillSpeedDownTime\":0,\"SkillIndicatorType\":0,\"SkillIndicatorParam\":[],\"SkillIndicatorParamTagConfigIds\":[],\"SkillIndicatorResParam\":[],\"SkillIndicatorResParamTagConfigIds\":[],\"LockEntityAfterUseSkillDuration\":0,\"LockEntityPosTypeAfterUseSkill\":0,\"SkillEffectOnSkillCastInterrupt\":0,\"UseSkillForbidUpdateFaceDir\":false,\"UseType\":0,\"ButtonUpConfig\":0,\"InterruptConfig\":0,\"ReActiveConfig\":0,\"SkillQuality\":0,\"IsPassiveSkillHideCD\":false,\"IsPassiveSkillNotRunByCD\":false,\"SkillProperty\":0,\"SkillRangeTagConfigId\":0,\"SkillMinRangeTagConfigId\":0,\"SmartCastTargetBasePriority\":3,\"SmartCastTargetCondTemplate\":1,\"SmartCastTargetMonsterRankCond\":[16,15,14,13,12,11,4,5,6,0],\"SmartCastTargetCampCond\":[2],\"SmartCastNoTargetIndicatorPos\":0,\"SmartCastNoTargetCancelUse\":false,\"CastTargetCondTemplate\":1,\"CastTargetMonsterRankCond\":[16,15,14,13,12,11,4,5,6,0],\"CastTargetCampCond\":[2],\"IsHideContinueUseSkillHeadBar\":false,\"SkillPriority\":0,\"EnhanceSkillBuffConfigID\":0,\"StatisticsDamageAloneForSummon\":false}",
                    "Config2ID": "SkillConfig_31031016"
                }
            },
            {
                "rid": 1001,
                "type": {
                    "class": "TSET_ORDER_EXECUTE",
                    "ns": "NodeEditor",
                    "asm": "NodeEditor"
                },
                "data": {
                    "GUID": "79af6a7f-fd86-4437-8f2a-96c564eeba75",
                    "computeOrder": 1,
                    "position": {
                        "serializedVersion": "2",
                        "x": 375.0,
                        "y": 355.0,
                        "width": 266.0,
                        "height": 94.0
                    },
                    "expanded": false,
                    "debug": false,
                    "nodeLock": false,
                    "visible": true,
                    "hideChildNodes": false,
                    "hidePos": {
                        "x": 0.0,
                        "y": 0.0
                    },
                    "hideCounter": 0,
                    "ID": 220002474,
                    "Desc": "",
                    "IsTemplate": false,
                    "TemplateFlags": 0,
                    "TemplateParams": [],
                    "TemplateParamsDesc": [],
                    "TemplateParamsCustomAdd": false,
                    "TableTash": "0CFA05568A66FEA1DF3BA6FE40DB7080",
                    "ConfigJson": "{\"ID\":220002474,\"SkillEffectType\":1,\"Params\":[{\"Value\":220002477,\"ParamType\":0,\"Factor\":0}]}",
                    "Config2ID": "SkillEffectConfig_220002474",
                    "SkillEffectType": 1
                }
            },
            {
                "rid": 1002,
                "type": {
                    "class": "TSET_REGISTER_SKILL_EVENT",
                    "ns": "NodeEditor",
                    "asm": "NodeEditor"
                },
                "data": {
                    "GUID": "eb3a010d-1db0-44fb-a2d6-d2b399b5dad9",
                    "computeOrder": 2,
                    "position": {
                        "serializedVersion": "2",
                        "x": 722.0,
                        "y": 357.0,
                        "width": 329.0,
                        "height": 334.0
                    },
                    "expanded": false,
                    "debug": false,
                    "nodeLock": false,
                    "visible": true,
                    "hideChildNodes": false,
                    "hidePos": {
                        "x": 0.0,
                        "y": 0.0
                    },
                    "hideCounter": 0,
                    "ID": 220002477,
                    "Desc": "",
                    "IsTemplate": false,
                    "TemplateFlags": 0,
                    "TemplateParams": [],
                    "TemplateParamsDesc": [],
                    "TemplateParamsCustomAdd": false,
                    "TableTash": "0CFA05568A66FEA1DF3BA6FE40DB7080",
                    "ConfigJson": "{\"ID\":220002477,\"SkillEffectType\":68,\"Params\":[{\"Value\":11,\"ParamType\":0,\"Factor\":0},{\"Value\":220002478,\"ParamType\":0,\"Factor\":0},{\"Value\":0,\"ParamType\":0,\"Factor\":0},{\"Value\":0,\"ParamType\":0,\"Factor\":0},{\"Value\":2200434,\"ParamType\":0,\"Factor\":0},{\"Value\":30,\"ParamType\":0,\"Factor\":0},{\"Value\":4,\"ParamType\":0,\"Factor\":0},{\"Value\":0,\"ParamType\":0,\"Factor\":0},{\"Value\":1,\"ParamType\":0,\"Factor\":0},{\"Value\":0,\"ParamType\":0,\"Factor\":0},{\"Value\":0,\"ParamType\":0,\"Factor\":0}]}",
                    "Config2ID": "SkillEffectConfig_220002477",
                    "SkillEffectType": 68
                }
            },
            {
                "rid": 1003,
                "type": {
                    "class": "TSET_ORDER_EXECUTE",
                    "ns": "NodeEditor",
                    "asm": "NodeEditor"
                },
                "data": {
                    "GUID": "a36e6ff6-62e0-4baf-abcc-9fe624224ecd",
                    "computeOrder": 3,
                    "position": {
                        "serializedVersion": "2",
                        "x": 1309.6500244140625,
                        "y": 302.95001220703127,
                        "width": 266.0001220703125,
                        "height": 94.0
                    },
                    "expanded": false,
                    "debug": false,
                    "nodeLock": false,
                    "visible": true,
                    "hideChildNodes": false,
                    "hidePos": {
                        "x": 0.0,
                        "y": 0.0
                    },
                    "hideCounter": 0,
                    "ID": 220002478,
                    "Desc": "",
                    "IsTemplate": false,
                    "TemplateFlags": 0,
                    "TemplateParams": [],
                    "TemplateParamsDesc": [],
                    "TemplateParamsCustomAdd": false,
                    "TableTash": "0CFA05568A66FEA1DF3BA6FE40DB7080",
                    "ConfigJson": "{\"ID\":220002478,\"SkillEffectType\":1,\"Params\":[{\"Value\":220002479,\"ParamType\":0,\"Factor\":0},{\"Value\":220002480,\"ParamType\":0,\"Factor\":0}]}",
                    "Config2ID": "SkillEffectConfig_220002478",
                    "SkillEffectType": 1
                }
            },
            {
                "rid": 1004,
                "type": {
                    "class": "TSET_CONDITION_EXECUTE",
                    "ns": "NodeEditor",
                    "asm": "NodeEditor"
                },
                "data": {
                    "GUID": "68e56963-d0b9-4d73-b1a8-c320a5b29420",
                    "computeOrder": 4,
                    "position": {
                        "serializedVersion": "2",
                        "x": 1613.6502685546875,
                        "y": 336.9500427246094,
                        "width": 321.9998779296875,
                        "height": 142.00006103515626
                    },
                    "expanded": false,
                    "debug": false,
                    "nodeLock": false,
                    "visible": true,
                    "hideChildNodes": false,
                    "hidePos": {
                        "x": 0.0,
                        "y": 0.0
                    },
                    "hideCounter": 0,
                    "ID": 220002480,
                    "Desc": "",
                    "IsTemplate": false,
                    "TemplateFlags": 0,
                    "TemplateParams": [],
                    "TemplateParamsDesc": [],
                    "TemplateParamsCustomAdd": false,
                    "TableTash": "0CFA05568A66FEA1DF3BA6FE40DB7080",
                    "ConfigJson": "{\"ID\":220002480,\"SkillEffectType\":47,\"Params\":[{\"Value\":2200407,\"ParamType\":0,\"Factor\":0},{\"Value\":220002482,\"ParamType\":0,\"Factor\":0},{\"Value\":0,\"ParamType\":0,\"Factor\":0}]}",
                    "Config2ID": "SkillEffectConfig_220002480",
                    "SkillEffectType": 47
                }
            },
            {
                "rid": 1005,
                "type": {
                    "class": "TSET_ADD_SKILL_TAG_VALUE",
                    "ns": "NodeEditor",
                    "asm": "NodeEditor"
                },
                "data": {
                    "GUID": "1f4a3cd6-aaa2-44fe-ba7c-30c5c2c1ee75",
                    "computeOrder": 5,
                    "position": {
                        "serializedVersion": "2",
                        "x": 1620.650146484375,
                        "y": -23.050020217895509,
                        "width": 427.0,
                        "height": 190.00003051757813
                    },
                    "expanded": false,
                    "debug": false,
                    "nodeLock": false,
                    "visible": true,
                    "hideChildNodes": false,
                    "hidePos": {
                        "x": 0.0,
                        "y": 0.0
                    },
                    "hideCounter": 0,
                    "ID": 220002479,
                    "Desc": "",
                    "IsTemplate": false,
                    "TemplateFlags": 0,
                    "TemplateParams": [],
                    "TemplateParamsDesc": [],
                    "TemplateParamsCustomAdd": false,
                    "TableTash": "0CFA05568A66FEA1DF3BA6FE40DB7080",
                    "ConfigJson": "{\"ID\":220002479,\"SkillEffectType\":97,\"Params\":[{\"Value\":4,\"ParamType\":5,\"Factor\":0},{\"Value\":41,\"ParamType\":5,\"Factor\":0},{\"Value\":1001,\"ParamType\":0,\"Factor\":0},{\"Value\":1,\"ParamType\":0,\"Factor\":0},{\"Value\":1,\"ParamType\":0,\"Factor\":0}]}",
                    "Config2ID": "SkillEffectConfig_220002479",
                    "SkillEffectType": 97
                }
            },
            {
                "rid": 1006,
                "type": {
                    "class": "TSCT_VALUE_COMPARE",
                    "ns": "NodeEditor",
                    "asm": "NodeEditor"
                },
                "data": {
                    "GUID": "7bbad3f7-e748-4f43-9559-5e2cc4cc6e54",
                    "computeOrder": 6,
                    "position": {
                        "serializedVersion": "2",
                        "x": 2122.650390625,
                        "y": 141.95001220703126,
                        "width": 272.0,
                        "height": 142.00003051757813
                    },
                    "expanded": false,
                    "debug": false,
                    "nodeLock": false,
                    "visible": true,
                    "hideChildNodes": false,
                    "hidePos": {
                        "x": 0.0,
                        "y": 0.0
                    },
                    "hideCounter": 0,
                    "ID": 2200407,
                    "Desc": "",
                    "IsTemplate": false,
                    "TemplateFlags": 0,
                    "TemplateParams": [],
                    "TemplateParamsDesc": [],
                    "TemplateParamsCustomAdd": false,
                    "TableTash": "ED89F46EAB95F7ACF5C1911A5A375278",
                    "ConfigJson": "{\"ID\":2200407,\"SkillConditionType\":7,\"Params\":[{\"Value\":220002481,\"ParamType\":2,\"Factor\":0},{\"Value\":4,\"ParamType\":0,\"Factor\":0},{\"Value\":30,\"ParamType\":0,\"Factor\":0}]}",
                    "Config2ID": "SkillConditionConfig_2200407",
                    "SkillConditionType": 7
                }
            },
            {
                "rid": 1007,
                "type": {
                    "class": "TSET_GET_SKILL_TAG_VALUE",
                    "ns": "NodeEditor",
                    "asm": "NodeEditor"
                },
                "data": {
                    "GUID": "62f9de12-b84c-4ddb-be6f-8108606d01f6",
                    "computeOrder": 7,
                    "position": {
                        "serializedVersion": "2",
                        "x": 2430.650146484375,
                        "y": 141.95001220703126,
                        "width": 426.000244140625,
                        "height": 190.0
                    },
                    "expanded": false,
                    "debug": false,
                    "nodeLock": false,
                    "visible": true,
                    "hideChildNodes": false,
                    "hidePos": {
                        "x": 0.0,
                        "y": 0.0
                    },
                    "hideCounter": 0,
                    "ID": 220002481,
                    "Desc": "",
                    "IsTemplate": false,
                    "TemplateFlags": 0,
                    "TemplateParams": [],
                    "TemplateParamsDesc": [],
                    "TemplateParamsCustomAdd": false,
                    "TableTash": "0CFA05568A66FEA1DF3BA6FE40DB7080",
                    "ConfigJson": "{\"ID\":220002481,\"SkillEffectType\":48,\"Params\":[{\"Value\":4,\"ParamType\":5,\"Factor\":0},{\"Value\":41,\"ParamType\":5,\"Factor\":0},{\"Value\":1001,\"ParamType\":0,\"Factor\":0},{\"Value\":1,\"ParamType\":0,\"Factor\":0},{\"Value\":1,\"ParamType\":0,\"Factor\":0}]}",
                    "Config2ID": "SkillEffectConfig_220002481",
                    "SkillEffectType": 48
                }
            },
            {
                "rid": 1008,
                "type": {
                    "class": "TSET_ORDER_EXECUTE",
                    "ns": "NodeEditor",
                    "asm": "NodeEditor"
                },
                "data": {
                    "GUID": "de511fd5-56ae-407a-b55a-57cb02033a5f",
                    "computeOrder": 8,
                    "position": {
                        "serializedVersion": "2",
                        "x": 2150.64990234375,
                        "y": 575.9500732421875,
                        "width": 267.00048828125,
                        "height": 93.99993896484375
                    },
                    "expanded": false,
                    "debug": false,
                    "nodeLock": false,
                    "visible": true,
                    "hideChildNodes": false,
                    "hidePos": {
                        "x": 0.0,
                        "y": 0.0
                    },
                    "hideCounter": 0,
                    "ID": 220002482,
                    "Desc": "",
                    "IsTemplate": false,
                    "TemplateFlags": 0,
                    "TemplateParams": [],
                    "TemplateParamsDesc": [],
                    "TemplateParamsCustomAdd": false,
                    "TableTash": "0CFA05568A66FEA1DF3BA6FE40DB7080",
                    "ConfigJson": "{\"ID\":220002482,\"SkillEffectType\":1,\"Params\":[{\"Value\":220002498,\"ParamType\":0,\"Factor\":0},{\"Value\":220002558,\"ParamType\":0,\"Factor\":0},{\"Value\":220002721,\"ParamType\":0,\"Factor\":0}]}",
                    "Config2ID": "SkillEffectConfig_220002482",
                    "SkillEffectType": 1
                }
            },
            {
                "rid": 1009,
                "type": {
                    "class": "TSET_ADD_BUFF",
                    "ns": "NodeEditor",
                    "asm": "NodeEditor"
                },
                "data": {
                    "GUID": "2b5fa0fa-2b5d-4d95-a3fd-28a9830b925a",
                    "computeOrder": 9,
                    "position": {
                        "serializedVersion": "2",
                        "x": 2492.650390625,
                        "y": 433.9501037597656,
                        "width": 341.0,
                        "height": 237.99990844726563
                    },
                    "expanded": false,
                    "debug": false,
                    "nodeLock": false,
                    "visible": true,
                    "hideChildNodes": false,
                    "hidePos": {
                        "x": 0.0,
                        "y": 0.0
                    },
                    "hideCounter": 0,
                    "ID": 220002498,
                    "Desc": "",
                    "IsTemplate": false,
                    "TemplateFlags": 0,
                    "TemplateParams": [],
                    "TemplateParamsDesc": [],
                    "TemplateParamsCustomAdd": false,
                    "TableTash": "0CFA05568A66FEA1DF3BA6FE40DB7080",
                    "ConfigJson": "{\"ID\":220002498,\"SkillEffectType\":4,\"Params\":[{\"Value\":3,\"ParamType\":5,\"Factor\":0},{\"Value\":3,\"ParamType\":5,\"Factor\":0},{\"Value\":2200083,\"ParamType\":0,\"Factor\":0},{\"Value\":0,\"ParamType\":0,\"Factor\":0},{\"Value\":0,\"ParamType\":0,\"Factor\":0},{\"Value\":1,\"ParamType\":0,\"Factor\":0},{\"Value\":1,\"ParamType\":0,\"Factor\":0}]}",
                    "Config2ID": "SkillEffectConfig_220002498",
                    "SkillEffectType": 4
                }
            },
            {
                "rid": 1010,
                "type": {
                    "class": "TSET_NUM_CALCULATE",
                    "ns": "NodeEditor",
                    "asm": "NodeEditor"
                },
                "data": {
                    "GUID": "44ab04cc-f422-410b-a78a-50981e7167fa",
                    "computeOrder": 10,
                    "position": {
                        "serializedVersion": "2",
                        "x": 1279.0606689453125,
                        "y": -1580.8004150390625,
                        "width": 265.0,
                        "height": 142.0
                    },
                    "expanded": false,
                    "debug": false,
                    "nodeLock": false,
                    "visible": true,
                    "hideChildNodes": false,
                    "hidePos": {
                        "x": 0.0,
                        "y": 0.0
                    },
                    "hideCounter": 0,
                    "ID": 220005100,
                    "Desc": "",
                    "IsTemplate": false,
                    "TemplateFlags": 0,
                    "TemplateParams": [],
                    "TemplateParamsDesc": [],
                    "TemplateParamsCustomAdd": false,
                    "TableTash": "0CFA05568A66FEA1DF3BA6FE40DB7080",
                    "ConfigJson": "{\"ID\":220005100,\"SkillEffectType\":31,\"Params\":[{\"Value\":220005096,\"ParamType\":2,\"Factor\":0},{\"Value\":3,\"ParamType\":0,\"Factor\":0},{\"Value\":220005098,\"ParamType\":2,\"Factor\":0}]}",
                    "Config2ID": "SkillEffectConfig_220005100",
                    "SkillEffectType": 31
                }
            },
            {
                "rid": 1011,
                "type": {
                    "class": "TSET_MODIFY_SKILL_TAG_VALUE",
                    "ns": "NodeEditor",
                    "asm": "NodeEditor"
                },
                "data": {
                    "GUID": "35f9fcc6-bc26-44c3-90ca-91c48e34d31e",
                    "computeOrder": 11,
                    "position": {
                        "serializedVersion": "2",
                        "x": 2489.64990234375,
                        "y": 768.9501342773438,
                        "width": 427.0,
                        "height": 189.9998779296875
                    },
                    "expanded": false,
                    "debug": false,
                    "nodeLock": false,
                    "visible": true,
                    "hideChildNodes": false,
                    "hidePos": {
                        "x": 0.0,
                        "y": 0.0
                    },
                    "hideCounter": 0,
                    "ID": 220002558,
                    "Desc": "",
                    "IsTemplate": false,
                    "TemplateFlags": 0,
                    "TemplateParams": [],
                    "TemplateParamsDesc": [],
                    "TemplateParamsCustomAdd": false,
                    "TableTash": "0CFA05568A66FEA1DF3BA6FE40DB7080",
                    "ConfigJson": "{\"ID\":220002558,\"SkillEffectType\":46,\"Params\":[{\"Value\":4,\"ParamType\":5,\"Factor\":0},{\"Value\":41,\"ParamType\":5,\"Factor\":0},{\"Value\":1001,\"ParamType\":0,\"Factor\":0},{\"Value\":0,\"ParamType\":0,\"Factor\":0},{\"Value\":1,\"ParamType\":0,\"Factor\":0}]}",
                    "Config2ID": "SkillEffectConfig_220002558",
                    "SkillEffectType": 46
                }
            },
            {
                "rid": 1012,
                "type": {
                    "class": "TSET_GET_SKILL_TAG_VALUE",
                    "ns": "NodeEditor",
                    "asm": "NodeEditor"
                },
                "data": {
                    "GUID": "b6a8df7a-5131-4f53-8beb-743c20436612",
                    "computeOrder": 12,
                    "position": {
                        "serializedVersion": "2",
                        "x": 1630.0606689453125,
                        "y": -1841.8004150390625,
                        "width": 428.0,
                        "height": 190.0
                    },
                    "expanded": false,
                    "debug": false,
                    "nodeLock": false,
                    "visible": true,
                    "hideChildNodes": false,
                    "hidePos": {
                        "x": 0.0,
                        "y": 0.0
                    },
                    "hideCounter": 0,
                    "ID": 220005096,
                    "Desc": "",
                    "IsTemplate": false,
                    "TemplateFlags": 0,
                    "TemplateParams": [],
                    "TemplateParamsDesc": [],
                    "TemplateParamsCustomAdd": false,
                    "TableTash": "0CFA05568A66FEA1DF3BA6FE40DB7080",
                    "ConfigJson": "{\"ID\":220005096,\"SkillEffectType\":48,\"Params\":[{\"Value\":4,\"ParamType\":5,\"Factor\":0},{\"Value\":41,\"ParamType\":5,\"Factor\":0},{\"Value\":2200079,\"ParamType\":0,\"Factor\":0},{\"Value\":1,\"ParamType\":0,\"Factor\":0},{\"Value\":1,\"ParamType\":0,\"Factor\":0}]}",
                    "Config2ID": "SkillEffectConfig_220005096",
                    "SkillEffectType": 48
                }
            },
            {
                "rid": 1013,
                "type": {
                    "class": "TSET_NUM_CALCULATE",
                    "ns": "NodeEditor",
                    "asm": "NodeEditor"
                },
                "data": {
                    "GUID": "8726de9e-7513-4b20-8343-756f8bcf4417",
                    "computeOrder": 13,
                    "position": {
                        "serializedVersion": "2",
                        "x": 1616.0606689453125,
                        "y": -1443.8004150390625,
                        "width": 267.0,
                        "height": 190.0
                    },
                    "expanded": false,
                    "debug": false,
                    "nodeLock": false,
                    "visible": true,
                    "hideChildNodes": false,
                    "hidePos": {
                        "x": 1195.0,
                        "y": -255.0
                    },
                    "hideCounter": 0,
                    "ID": 220005098,
                    "Desc": "",
                    "IsTemplate": false,
                    "TemplateFlags": 0,
                    "TemplateParams": [],
                    "TemplateParamsDesc": [],
                    "TemplateParamsCustomAdd": false,
                    "TableTash": "0CFA05568A66FEA1DF3BA6FE40DB7080",
                    "ConfigJson": "{\"ID\":220005098,\"SkillEffectType\":31,\"Params\":[{\"Value\":220005097,\"ParamType\":2,\"Factor\":0},{\"Value\":6,\"ParamType\":0,\"Factor\":0},{\"Value\":10000,\"ParamType\":0,\"Factor\":0},{\"Value\":5,\"ParamType\":0,\"Factor\":0},{\"Value\":220005099,\"ParamType\":2,\"Factor\":0}]}",
                    "Config2ID": "SkillEffectConfig_220005098",
                    "SkillEffectType": 31
                }
            },
            {
                "rid": 1014,
                "type": {
                    "class": "BuffConfigNode",
                    "ns": "NodeEditor",
                    "asm": "NodeEditor"
                },
                "data": {
                    "GUID": "44fdc264-5260-4b97-97e8-42e59fe8a903",
                    "computeOrder": 14,
                    "position": {
                        "serializedVersion": "2",
                        "x": 2927.650146484375,
                        "y": 482.9500427246094,
                        "width": 289.0,
                        "height": 230.99996948242188
                    },
                    "expanded": false,
                    "debug": false,
                    "nodeLock": false,
                    "visible": true,
                    "hideChildNodes": false,
                    "hidePos": {
                        "x": 0.0,
                        "y": 0.0
                    },
                    "hideCounter": 0,
                    "ID": 2200083,
                    "Desc": "",
                    "IsTemplate": false,
                    "TemplateFlags": 0,
                    "TemplateParams": [],
                    "TemplateParamsDesc": [],
                    "TemplateParamsCustomAdd": false,
                    "TableTash": "209F32727A301A2C2835D2DDCF0D3251",
                    "ConfigJson": "{\"ID\":2200083,\"BuffNameKey\":2778661301,\"BuffDescKey\":4027175911,\"EffectID\":4,\"EffectIsOverlay\":false,\"Icon\":\"Buff/BF0007_i_01\",\"IsShowIcon\":true,\"ShowIconVisibleType\":0,\"IsHideUiProgress\":false,\"IconPriority\":0,\"BuffTypeFlags\":0,\"BuffLevel\":0,\"LastTime\":180,\"LoopTime\":0,\"OverlyingMax\":0,\"IsRefreshTime\":false,\"SameCoexistType\":0,\"DiffCoexistType\":0,\"IsSkillLevelHighReplaceLow\":false,\"BuffGroups\":[],\"RemoveOtherBuffGroups\":[],\"IsDeadExist\":false,\"AddState\":0,\"EffectAttrsOnlySelf\":false,\"Attrs\":[{\"AttrType\":175,\"Param\":{\"Value\":220005100,\"ParamType\":2,\"Factor\":0},\"OnlyApplyMaxValue\":false},{\"AttrType\":201,\"Param\":{\"Value\":220005105,\"ParamType\":3,\"Factor\":0},\"OnlyApplyMaxValue\":false}],\"IsTempAttrs\":true,\"SkillTags\":[],\"IsTempSkillTags\":true,\"IsIgnoreStateRules\":false,\"TagIcon\":\"\",\"MarkResourcePath\":\"\",\"MarkResourceShowType\":0,\"MarkResourceShowPos\":0,\"MarkResourceShowAnim\":false,\"MarkResourceShowFullEffect\":false,\"StatisticsDamageAloneForSummon\":false,\"FuryTimerBuff\":false,\"BuffNameEditor\":\"塔被动\",\"BuffDescEditor\":\"获得攻速与招式伤害增加。\"}",
                    "Config2ID": "BuffConfig_2200083"
                }
            },
            {
                "rid": 1015,
                "type": {
                    "class": "TSET_NUM_CALCULATE",
                    "ns": "NodeEditor",
                    "asm": "NodeEditor"
                },
                "data": {
                    "GUID": "5439c5df-15f1-4e4a-9fe6-61c0206b73cb",
                    "computeOrder": 15,
                    "position": {
                        "serializedVersion": "2",
                        "x": 1245.0606689453125,
                        "y": -780.8004150390625,
                        "width": 265.0,
                        "height": 142.0
                    },
                    "expanded": false,
                    "debug": false,
                    "nodeLock": false,
                    "visible": true,
                    "hideChildNodes": false,
                    "hidePos": {
                        "x": 0.0,
                        "y": 0.0
                    },
                    "hideCounter": 0,
                    "ID": 220005105,
                    "Desc": "",
                    "IsTemplate": false,
                    "TemplateFlags": 0,
                    "TemplateParams": [],
                    "TemplateParamsDesc": [],
                    "TemplateParamsCustomAdd": false,
                    "TableTash": "0CFA05568A66FEA1DF3BA6FE40DB7080",
                    "ConfigJson": "{\"ID\":220005105,\"SkillEffectType\":31,\"Params\":[{\"Value\":220005101,\"ParamType\":2,\"Factor\":0},{\"Value\":3,\"ParamType\":0,\"Factor\":0},{\"Value\":220005103,\"ParamType\":2,\"Factor\":0}]}",
                    "Config2ID": "SkillEffectConfig_220005105",
                    "SkillEffectType": 31
                }
            },
            {
                "rid": 1016,
                "type": {
                    "class": "TSET_GET_SKILL_TAG_VALUE",
                    "ns": "NodeEditor",
                    "asm": "NodeEditor"
                },
                "data": {
                    "GUID": "52462c51-9f49-48c7-a843-cdf3bd0806e9",
                    "computeOrder": 16,
                    "position": {
                        "serializedVersion": "2",
                        "x": 1964.0606689453125,
                        "y": -1273.8004150390625,
                        "width": 388.0,
                        "height": 190.0
                    },
                    "expanded": false,
                    "debug": false,
                    "nodeLock": false,
                    "visible": true,
                    "hideChildNodes": false,
                    "hidePos": {
                        "x": 1543.0,
                        "y": -85.0
                    },
                    "hideCounter": 0,
                    "ID": 220005099,
                    "Desc": "",
                    "IsTemplate": false,
                    "TemplateFlags": 0,
                    "TemplateParams": [],
                    "TemplateParamsDesc": [],
                    "TemplateParamsCustomAdd": false,
                    "TableTash": "0CFA05568A66FEA1DF3BA6FE40DB7080",
                    "ConfigJson": "{\"ID\":220005099,\"SkillEffectType\":48,\"Params\":[{\"Value\":4,\"ParamType\":5,\"Factor\":0},{\"Value\":31310003,\"ParamType\":0,\"Factor\":0},{\"Value\":2200126,\"ParamType\":0,\"Factor\":0},{\"Value\":1,\"ParamType\":0,\"Factor\":0},{\"Value\":1,\"ParamType\":0,\"Factor\":0}]}",
                    "Config2ID": "SkillEffectConfig_220005099",
                    "SkillEffectType": 48
                }
            },
            {
                "rid": 1017,
                "type": {
                    "class": "TSET_GET_SKILL_TAG_VALUE",
                    "ns": "NodeEditor",
                    "asm": "NodeEditor"
                },
                "data": {
                    "GUID": "46a9423b-a29f-4a71-9241-dfd577dea193",
                    "computeOrder": 17,
                    "position": {
                        "serializedVersion": "2",
                        "x": 1594.0606689453125,
                        "y": -1040.8004150390625,
                        "width": 424.0,
                        "height": 190.0
                    },
                    "expanded": false,
                    "debug": false,
                    "nodeLock": false,
                    "visible": true,
                    "hideChildNodes": false,
                    "hidePos": {
                        "x": 0.0,
                        "y": 0.0
                    },
                    "hideCounter": 0,
                    "ID": 220005101,
                    "Desc": "",
                    "IsTemplate": false,
                    "TemplateFlags": 0,
                    "TemplateParams": [],
                    "TemplateParamsDesc": [],
                    "TemplateParamsCustomAdd": false,
                    "TableTash": "0CFA05568A66FEA1DF3BA6FE40DB7080",
                    "ConfigJson": "{\"ID\":220005101,\"SkillEffectType\":48,\"Params\":[{\"Value\":4,\"ParamType\":5,\"Factor\":0},{\"Value\":41,\"ParamType\":5,\"Factor\":0},{\"Value\":2200080,\"ParamType\":0,\"Factor\":0},{\"Value\":1,\"ParamType\":0,\"Factor\":0},{\"Value\":1,\"ParamType\":0,\"Factor\":0}]}",
                    "Config2ID": "SkillEffectConfig_220005101",
                    "SkillEffectType": 48
                }
            },
            {
                "rid": 1018,
                "type": {
                    "class": "TSET_NUM_CALCULATE",
                    "ns": "NodeEditor",
                    "asm": "NodeEditor"
                },
                "data": {
                    "GUID": "9cd75ccd-f5c1-41c2-afed-87a470f89867",
                    "computeOrder": 18,
                    "position": {
                        "serializedVersion": "2",
                        "x": 1579.0606689453125,
                        "y": -642.8004150390625,
                        "width": 265.0,
                        "height": 190.0
                    },
                    "expanded": false,
                    "debug": false,
                    "nodeLock": false,
                    "visible": true,
                    "hideChildNodes": false,
                    "hidePos": {
                        "x": 1195.0,
                        "y": -255.0
                    },
                    "hideCounter": 0,
                    "ID": 220005103,
                    "Desc": "",
                    "IsTemplate": false,
                    "TemplateFlags": 0,
                    "TemplateParams": [],
                    "TemplateParamsDesc": [],
                    "TemplateParamsCustomAdd": false,
                    "TableTash": "0CFA05568A66FEA1DF3BA6FE40DB7080",
                    "ConfigJson": "{\"ID\":220005103,\"SkillEffectType\":31,\"Params\":[{\"Value\":220005102,\"ParamType\":2,\"Factor\":0},{\"Value\":6,\"ParamType\":0,\"Factor\":0},{\"Value\":10000,\"ParamType\":0,\"Factor\":0},{\"Value\":5,\"ParamType\":0,\"Factor\":0},{\"Value\":220005104,\"ParamType\":2,\"Factor\":0}]}",
                    "Config2ID": "SkillEffectConfig_220005103",
                    "SkillEffectType": 31
                }
            },
            {
                "rid": 1019,
                "type": {
                    "class": "TSET_GET_SKILL_TAG_VALUE",
                    "ns": "NodeEditor",
                    "asm": "NodeEditor"
                },
                "data": {
                    "GUID": "acc17d7d-c286-4e97-9152-2bd9196fc997",
                    "computeOrder": 19,
                    "position": {
                        "serializedVersion": "2",
                        "x": 1964.0606689453125,
                        "y": -1512.8004150390625,
                        "width": 427.0,
                        "height": 190.0
                    },
                    "expanded": false,
                    "debug": false,
                    "nodeLock": false,
                    "visible": true,
                    "hideChildNodes": false,
                    "hidePos": {
                        "x": 1543.0,
                        "y": -324.0
                    },
                    "hideCounter": 0,
                    "ID": 220005097,
                    "Desc": "",
                    "IsTemplate": false,
                    "TemplateFlags": 0,
                    "TemplateParams": [],
                    "TemplateParamsDesc": [],
                    "TemplateParamsCustomAdd": false,
                    "TableTash": "0CFA05568A66FEA1DF3BA6FE40DB7080",
                    "ConfigJson": "{\"ID\":220005097,\"SkillEffectType\":48,\"Params\":[{\"Value\":4,\"ParamType\":5,\"Factor\":0},{\"Value\":41,\"ParamType\":5,\"Factor\":0},{\"Value\":2200079,\"ParamType\":0,\"Factor\":0},{\"Value\":1,\"ParamType\":0,\"Factor\":0},{\"Value\":1,\"ParamType\":0,\"Factor\":0}]}",
                    "Config2ID": "SkillEffectConfig_220005097",
                    "SkillEffectType": 48
                }
            },
            {
                "rid": 1020,
                "type": {
                    "class": "TSET_GET_SKILL_TAG_VALUE",
                    "ns": "NodeEditor",
                    "asm": "NodeEditor"
                },
                "data": {
                    "GUID": "71bf71ea-e249-4b3e-bea5-af4d7b53f3ba",
                    "computeOrder": 20,
                    "position": {
                        "serializedVersion": "2",
                        "x": 1931.0606689453125,
                        "y": -483.8004150390625,
                        "width": 386.0,
                        "height": 190.0
                    },
                    "expanded": false,
                    "debug": false,
                    "nodeLock": false,
                    "visible": true,
                    "hideChildNodes": false,
                    "hidePos": {
                        "x": 1543.0,
                        "y": -85.0
                    },
                    "hideCounter": 0,
                    "ID": 220005104,
                    "Desc": "",
                    "IsTemplate": false,
                    "TemplateFlags": 0,
                    "TemplateParams": [],
                    "TemplateParamsDesc": [],
                    "TemplateParamsCustomAdd": false,
                    "TableTash": "0CFA05568A66FEA1DF3BA6FE40DB7080",
                    "ConfigJson": "{\"ID\":220005104,\"SkillEffectType\":48,\"Params\":[{\"Value\":4,\"ParamType\":5,\"Factor\":0},{\"Value\":31310003,\"ParamType\":0,\"Factor\":0},{\"Value\":2200126,\"ParamType\":0,\"Factor\":0},{\"Value\":1,\"ParamType\":0,\"Factor\":0},{\"Value\":1,\"ParamType\":0,\"Factor\":0}]}",
                    "Config2ID": "SkillEffectConfig_220005104",
                    "SkillEffectType": 48
                }
            },
            {
                "rid": 1021,
                "type": {
                    "class": "TSET_GET_SKILL_TAG_VALUE",
                    "ns": "NodeEditor",
                    "asm": "NodeEditor"
                },
                "data": {
                    "GUID": "2fb69f21-8c97-4c35-85fb-6517bc4e2a1f",
                    "computeOrder": 21,
                    "position": {
                        "serializedVersion": "2",
                        "x": 1928.0606689453125,
                        "y": -710.8004150390625,
                        "width": 426.0,
                        "height": 190.0
                    },
                    "expanded": false,
                    "debug": false,
                    "nodeLock": false,
                    "visible": true,
                    "hideChildNodes": false,
                    "hidePos": {
                        "x": 1543.0,
                        "y": -324.0
                    },
                    "hideCounter": 0,
                    "ID": 220005102,
                    "Desc": "",
                    "IsTemplate": false,
                    "TemplateFlags": 0,
                    "TemplateParams": [],
                    "TemplateParamsDesc": [],
                    "TemplateParamsCustomAdd": false,
                    "TableTash": "0CFA05568A66FEA1DF3BA6FE40DB7080",
                    "ConfigJson": "{\"ID\":220005102,\"SkillEffectType\":48,\"Params\":[{\"Value\":4,\"ParamType\":5,\"Factor\":0},{\"Value\":41,\"ParamType\":5,\"Factor\":0},{\"Value\":2200080,\"ParamType\":0,\"Factor\":0},{\"Value\":1,\"ParamType\":0,\"Factor\":0},{\"Value\":1,\"ParamType\":0,\"Factor\":0}]}",
                    "Config2ID": "SkillEffectConfig_220005102",
                    "SkillEffectType": 48
                }
            },
            {
                "rid": 1022,
                "type": {
                    "class": "SkillTagsConfigNode",
                    "ns": "NodeEditor",
                    "asm": "NodeEditor"
                },
                "data": {
                    "GUID": "d49a62b1-3997-49cb-bc89-d0f8a0701e79",
                    "computeOrder": 22,
                    "position": {
                        "serializedVersion": "2",
                        "x": 614.1232299804688,
                        "y": 74.47909545898438,
                        "width": 243.0,
                        "height": 94.00003051757813
                    },
                    "expanded": false,
                    "debug": false,
                    "nodeLock": false,
                    "visible": true,
                    "hideChildNodes": false,
                    "hidePos": {
                        "x": 0.0,
                        "y": 0.0
                    },
                    "hideCounter": 0,
                    "ID": 2200079,
                    "Desc": "",
                    "IsTemplate": false,
                    "TemplateFlags": 0,
                    "TemplateParams": [],
                    "TemplateParamsDesc": [],
                    "TemplateParamsCustomAdd": false,
                    "TableTash": "6A8A6883BDFDA1411BB2461E65CB2D9B",
                    "ConfigJson": "{\"ID\":2200079,\"TagType\":0,\"Desc\":\"塔攻击速度系数\",\"NameKey\":0,\"DefaultValue\":2000,\"FinalValueEffectID\":0,\"RetainWhenDie\":false,\"NameEditor\":\"塔攻击速度系数\"}",
                    "Config2ID": "SkillTagsConfig_2200079"
                }
            },
            {
                "rid": 1023,
                "type": {
                    "class": "SkillTagsConfigNode",
                    "ns": "NodeEditor",
                    "asm": "NodeEditor"
                },
                "data": {
                    "GUID": "f72361cf-8b26-4759-b71b-4d65f16ec730",
                    "computeOrder": 23,
                    "position": {
                        "serializedVersion": "2",
                        "x": 922.1738891601563,
                        "y": 66.43477630615235,
                        "width": 243.99993896484376,
                        "height": 135.0
                    },
                    "expanded": false,
                    "debug": false,
                    "nodeLock": false,
                    "visible": true,
                    "hideChildNodes": false,
                    "hidePos": {
                        "x": 0.0,
                        "y": 0.0
                    },
                    "hideCounter": 0,
                    "ID": 2200080,
                    "Desc": "",
                    "IsTemplate": false,
                    "TemplateFlags": 0,
                    "TemplateParams": [],
                    "TemplateParamsDesc": [],
                    "TemplateParamsCustomAdd": false,
                    "TableTash": "6A8A6883BDFDA1411BB2461E65CB2D9B",
                    "ConfigJson": "{\"ID\":2200080,\"TagType\":0,\"Desc\":\"塔普攻伤害提升系数\",\"NameKey\":0,\"DefaultValue\":2000,\"FinalValueEffectID\":0,\"RetainWhenDie\":false,\"NameEditor\":\"塔普攻伤害提升系数\"}",
                    "Config2ID": "SkillTagsConfig_2200080"
                }
            },
            {
                "rid": 1024,
                "type": {
                    "class": "TSET_DELAY_EXECUTE",
                    "ns": "NodeEditor",
                    "asm": "NodeEditor"
                },
                "data": {
                    "GUID": "de90292a-b4e4-4723-a2cc-f4b9ae903ac8",
                    "computeOrder": 24,
                    "position": {
                        "serializedVersion": "2",
                        "x": 2465.650390625,
                        "y": 1007.9502563476563,
                        "width": 339.0,
                        "height": 237.99969482421876
                    },
                    "expanded": false,
                    "debug": false,
                    "nodeLock": false,
                    "visible": true,
                    "hideChildNodes": false,
                    "hidePos": {
                        "x": 0.0,
                        "y": 0.0
                    },
                    "hideCounter": 0,
                    "ID": 220002721,
                    "Desc": "",
                    "IsTemplate": false,
                    "TemplateFlags": 0,
                    "TemplateParams": [],
                    "TemplateParamsDesc": [],
                    "TemplateParamsCustomAdd": false,
                    "TableTash": "0CFA05568A66FEA1DF3BA6FE40DB7080",
                    "ConfigJson": "{\"ID\":220002721,\"SkillEffectType\":2,\"Params\":[{\"Value\":900,\"ParamType\":0,\"Factor\":0},{\"Value\":220002723,\"ParamType\":0,\"Factor\":0},{\"Value\":0,\"ParamType\":0,\"Factor\":0},{\"Value\":0,\"ParamType\":0,\"Factor\":0},{\"Value\":0,\"ParamType\":0,\"Factor\":0},{\"Value\":0,\"ParamType\":0,\"Factor\":0},{\"Value\":0,\"ParamType\":0,\"Factor\":0}]}",
                    "Config2ID": "SkillEffectConfig_220002721",
                    "SkillEffectType": 2
                }
            },
            {
                "rid": 1025,
                "type": {
                    "class": "TSET_ORDER_EXECUTE",
                    "ns": "NodeEditor",
                    "asm": "NodeEditor"
                },
                "data": {
                    "GUID": "eb2ef52a-0148-4ad7-97b3-92671e48b1da",
                    "computeOrder": 25,
                    "position": {
                        "serializedVersion": "2",
                        "x": 2826.64990234375,
                        "y": 1122.9500732421875,
                        "width": 266.000244140625,
                        "height": 94.0
                    },
                    "expanded": false,
                    "debug": false,
                    "nodeLock": false,
                    "visible": true,
                    "hideChildNodes": false,
                    "hidePos": {
                        "x": 0.0,
                        "y": 0.0
                    },
                    "hideCounter": 0,
                    "ID": 220002723,
                    "Desc": "",
                    "IsTemplate": false,
                    "TemplateFlags": 0,
                    "TemplateParams": [],
                    "TemplateParamsDesc": [],
                    "TemplateParamsCustomAdd": false,
                    "TableTash": "0CFA05568A66FEA1DF3BA6FE40DB7080",
                    "ConfigJson": "{\"ID\":220002723,\"SkillEffectType\":1,\"Params\":[{\"Value\":220002477,\"ParamType\":0,\"Factor\":0}]}",
                    "Config2ID": "SkillEffectConfig_220002723",
                    "SkillEffectType": 1
                }
            },
            {
                "rid": 1026,
                "type": {
                    "class": "RefConfigBaseNode",
                    "ns": "NodeEditor",
                    "asm": "NodeEditor"
                },
                "data": {
                    "GUID": "90f3ef6c-aef5-42aa-a68e-9e2bab1a2ea6",
                    "computeOrder": 26,
                    "position": {
                        "serializedVersion": "2",
                        "x": 3156.650390625,
                        "y": 1139.9500732421875,
                        "width": 342.999755859375,
                        "height": 94.0
                    },
                    "expanded": false,
                    "debug": false,
                    "nodeLock": false,
                    "visible": true,
                    "hideChildNodes": false,
                    "hidePos": {
                        "x": 0.0,
                        "y": 0.0
                    },
                    "hideCounter": 0,
                    "TableManagerName": "TableDR.SkillEffectConfigManager",
                    "ID": 220002477,
                    "ManualID": 220002477
                }
            },
            {
                "rid": 1027,
                "type": {
                    "class": "TSCT_AND",
                    "ns": "NodeEditor",
                    "asm": "NodeEditor"
                },
                "data": {
                    "GUID": "8a4ca4fa-a387-478f-a9e0-cb3ec3e9fc31",
                    "computeOrder": 27,
                    "position": {
                        "serializedVersion": "2",
                        "x": 1130.0,
                        "y": 547.0,
                        "width": 261.0,
                        "height": 94.0
                    },
                    "expanded": false,
                    "debug": false,
                    "nodeLock": false,
                    "visible": true,
                    "hideChildNodes": false,
                    "hidePos": {
                        "x": 0.0,
                        "y": 0.0
                    },
                    "hideCounter": 0,
                    "ID": 2200434,
                    "Desc": "",
                    "IsTemplate": false,
                    "TemplateFlags": 0,
                    "TemplateParams": [],
                    "TemplateParamsDesc": [],
                    "TemplateParamsCustomAdd": false,
                    "TableTash": "ED89F46EAB95F7ACF5C1911A5A375278",
                    "ConfigJson": "{\"ID\":2200434,\"SkillConditionType\":1,\"Params\":[{\"Value\":2200438,\"ParamType\":0,\"Factor\":0}]}",
                    "Config2ID": "SkillConditionConfig_2200434",
                    "SkillConditionType": 1
                }
            },
            {
                "rid": 1028,
                "type": {
                    "class": "TSCT_VALUE_COMPARE",
                    "ns": "NodeEditor",
                    "asm": "NodeEditor"
                },
                "data": {
                    "GUID": "54416e0c-3ef5-4022-8753-48d895a20cde",
                    "computeOrder": 28,
                    "position": {
                        "serializedVersion": "2",
                        "x": 1428.0,
                        "y": 531.0,
                        "width": 276.0,
                        "height": 142.0
                    },
                    "expanded": false,
                    "debug": false,
                    "nodeLock": false,
                    "visible": true,
                    "hideChildNodes": false,
                    "hidePos": {
                        "x": 0.0,
                        "y": 0.0
                    },
                    "hideCounter": 0,
                    "ID": 2200438,
                    "Desc": "",
                    "IsTemplate": false,
                    "TemplateFlags": 0,
                    "TemplateParams": [],
                    "TemplateParamsDesc": [],
                    "TemplateParamsCustomAdd": false,
                    "TableTash": "ED89F46EAB95F7ACF5C1911A5A375278",
                    "ConfigJson": "{\"ID\":2200438,\"SkillConditionType\":7,\"Params\":[{\"Value\":1,\"ParamType\":6,\"Factor\":0},{\"Value\":1,\"ParamType\":0,\"Factor\":0},{\"Value\":3,\"ParamType\":5,\"Factor\":0}]}",
                    "Config2ID": "SkillConditionConfig_2200438",
                    "SkillConditionType": 7
                }
            }
        ]
    }
}